{"quest_id": 10029, "name": "第29階層", "description": "【主な敵】\n塔の装置 / ドラゴン系\n\n＜ドロップなし＞＜編成内での同ユニット禁止＞", "modifier_notes": ["ドロップなし", "編成内での同ユニット禁止"], "event": "英傑の塔", "event_category": "Tower", "mission_id": 110001, "map_no": 28, "level": 100, "multiplier": 1.0, "capacity": 8, "modifiers": [{"kind": "term", "influence": 24, "params": [10], "expression": "IsOverlapMember() != 1;", "expression_human": "it is not a duplicate of another unit in your team"}], "enemies": [{"enemy_id": 1, "source": "local", "count": 3, "form_count": 1, "tags": ["置物", "機械", "アーマー"], "fixture": true, "hp": 100000, "base_hp": 100000, "damage_type": "physical", "armor_defense": 600, "magic_defense": 60, "attack_speed": 1, "attack_wait": 1, "move_speed": 400.0, "gain_cost": 10, "dot_rate": 1.2999999523162842, "pattern_id": 2122224, "special_effect_id": 517, "master_id": 21076, "global_id": 1370}, {"enemy_id": 2, "source": "local", "count": 1, "form_count": 3, "hp": 250000, "base_hp": 250000, "damage_type": "magical", "armor_defense": 1200, "magic_defense": 40, "attack_speed": 1, "attack_wait": 1, "move_speed": 2400.0, "gain_cost": 3, "dot_rate": 1.5, "pattern_id": 2121456, "race_id": 2, "special_effect_id": 275, "change_to": 2, "master_id": 32311, "global_id": 5930, "to_global_id": 5931, "route_behaviour": {"transforms": [{}]}, "spawn_sec": 26}, {"enemy_id": 2, "source": "local", "count": 1, "form_index": 1, "form_count": 3, "hp": 250000, "base_hp": 250000, "damage_type": "magical", "armor_defense": 450, "magic_defense": 20, "attack_speed": 1, "attack_wait": 1, "move_speed": 600.0, "gain_cost": 3, "dot_rate": 1.5, "pattern_id": 2121472, "race_id": 2, "special_effect_id": 275, "change_to": 3, "master_id": 32312, "global_id": 5931, "to_global_id": 5932}, {"enemy_id": 2, "source": "local", "count": 1, "form_index": 2, "form_count": 3, "hp": 250000, "base_hp": 250000, "damage_type": "magical", "armor_defense": 450, "magic_defense": 20, "attack_speed": 1, "attack_wait": 1, "move_speed": 600.0, "gain_cost": 3, "dot_rate": 1.5, "pattern_id": 2121488, "race_id": 2, "special_effect_id": 475, "change_to": 1, "master_id": 32313, "global_id": 5932}, {"enemy_id": 5, "source": "local", "count": 3, "form_count": 1, "hp": 8000, "attack": 750, "base_hp": 8000, "base_attack": 750, "damage_type": "physical", "armor_defense": 400, "attack_speed": 90, "attack_wait": 10, "attack_interval": 181, "move_speed": 350.0, "gain_cost": 3, "dot_rate": 1.7999999523162842, "assassin_resist": 100, "transform_resist": 100, "pattern_id": 2098560, "race_id": 2, "master_id": 30223, "global_id": 3842, "spawn_sec": 30}, {"enemy_id": 6, "source": "local", "count": 12, "form_count": 1, "hp": 1200, "attack": 300, "base_hp": 1200, "base_attack": 300, "damage_type": "physical", "armor_defense": 50, "magic_defense": 30, "attack_speed": 10, "attack_wait": 10, "attack_interval": 49, "move_speed": 1500.0, "gain_cost": 1, "dot_rate": 1.2000000476837158, "assassin_resist": 1000, "transform_resist": 1000, "pattern_id": 2098416, "race_id": 2, "master_id": 85, "global_id": 84, "spawn_sec": 35}, {"enemy_id": 7, "source": "local", "count": 1, "form_count": 1, "hp": 60000, "attack": 1500, "base_hp": 60000, "base_attack": 1500, "damage_type": "magical", "armor_defense": 300, "magic_defense": 5, "attack_range": 200, "attack_speed": 60, "attack_wait": 60, "attack_interval": 271, "move_speed": 300.0, "gain_cost": 3, "dot_rate": 1.2999999523162842, "assassin_resist": 100, "transform_resist": 100, "pattern_id": 2098608, "race_id": 2, "missile_id": 14, "missile": {"speed": 6.0, "splash": 147}, "master_id": 21107, "global_id": 1401, "ranged": true, "spawn_sec": 52}, {"enemy_id": 8, "source": "local", "count": 12, "form_count": 1, "hp": 1000, "attack": 400, "base_hp": 1000, "base_attack": 400, "damage_type": "physical", "armor_defense": 150, "attack_speed": 20, "attack_wait": 10, "attack_interval": 86, "move_speed": 1500.0, "gain_cost": 1, "dot_rate": 1.2000000476837158, "assassin_resist": 1000, "transform_resist": 1000, "pattern_id": 2098592, "race_id": 2, "master_id": 148, "global_id": 147, "spawn_sec": 53}, {"enemy_id": 9, "source": "local", "count": 4, "form_count": 1, "hp": 6000, "attack": 500, "base_hp": 6000, "base_attack": 500, "damage_type": "magical", "armor_defense": 400, "attack_range": 160, "attack_speed": 60, "attack_wait": 60, "attack_interval": 181, "move_speed": 400.0, "gain_cost": 3, "dot_rate": 1.5, "assassin_resist": 100, "transform_resist": 100, "pattern_id": 2098544, "race_id": 2, "missile_id": 7, "missile": {"speed": 6.0, "splash": 133}, "master_id": 293, "global_id": 292, "ranged": true, "spawn_sec": 62}, {"enemy_id": 10, "source": "local", "count": 7, "form_count": 2, "hp": 6000, "attack": 800, "base_hp": 6000, "base_attack": 800, "damage_type": "magical", "armor_defense": 300, "magic_defense": 30, "attack_range": 180, "attack_speed": 60, "attack_wait": 30, "attack_interval": 161, "move_speed": 250.0, "dot_rate": 1.600000023841858, "assassin_resist": 100, "transform_resist": 100, "pattern_id": 2100256, "race_id": 2, "change_to": 10, "change_condition": 2, "missile_id": 36, "missile": {"speed": 5.0, "splash": 160}, "master_id": 714, "global_id": 713, "ranged": true, "to_condition": 2, "to_global_id": 714, "spawn_sec": 74}, {"enemy_id": 10, "source": "local", "count": 1, "form_index": 1, "form_count": 2, "hp": 12000, "attack": 800, "base_hp": 12000, "base_attack": 800, "damage_type": "magical", "armor_defense": 400, "magic_defense": 30, "attack_range": 90, "attack_speed": 60, "attack_wait": 30, "attack_interval": 161, "move_speed": 200.0, "gain_cost": 3, "dot_rate": 1.600000023841858, "assassin_resist": 100, "transform_resist": 100, "pattern_id": 2100272, "race_id": 2, "missile_id": 36, "missile": {"speed": 5.0, "splash": 160}, "master_id": 715, "global_id": 714, "ranged": true, "from_condition": 2}, {"enemy_id": 12, "source": "local", "count": 12, "form_count": 1, "hp": 4000, "attack": 700, "base_hp": 4000, "base_attack": 700, "damage_type": "physical", "armor_defense": 300, "attack_speed": 90, "attack_wait": 10, "attack_interval": 171, "move_speed": 400.0, "gain_cost": 1, "dot_rate": 1.5, "assassin_resist": 100, "transform_resist": 100, "pattern_id": 2098528, "race_id": 2, "master_id": 297, "global_id": 296, "spawn_sec": 141}, {"enemy_id": 13, "source": "local", "count": 1, "form_count": 1, "hp": 120000, "attack": 2000, "base_hp": 120000, "base_attack": 2000, "damage_type": "magical", "armor_defense": 350, "magic_defense": 60, "attack_range": 230, "attack_speed": 60, "attack_wait": 60, "attack_interval": 181, "move_speed": 200.0, "gain_cost": 3, "dot_rate": 1.2999999523162842, "assassin_resist": 1, "transform_resist": 100, "pattern_id": 2100720, "race_id": 2, "special_effect_id": 232, "missile_id": 6, "master_id": 21108, "global_id": 1402, "ranged": true, "spawn_sec": 168}, {"enemy_id": 14, "source": "local", "count": 2, "form_count": 3, "hp": 10000, "attack": 500, "base_hp": 10000, "base_attack": 500, "damage_type": "magical", "armor_defense": 1000, "magic_defense": 80, "attack_speed": 60, "attack_wait": 30, "attack_interval": 221, "move_speed": 250.0, "dot_rate": 2.0, "assassin_resist": 1, "transform_resist": 1, "pattern_id": 2117696, "race_id": 2, "change_to": 14, "missile_id": 39, "missile": {"splash": 133}, "master_id": 31577, "global_id": 5196, "to_global_id": 5194, "route_behaviour": {"transforms": [{}]}, "spawn_sec": 178}, {"enemy_id": 14, "source": "local", "count": 1, "form_index": 1, "form_count": 3, "hp": 10000, "attack": 500, "base_hp": 10000, "base_attack": 500, "damage_type": "magical", "armor_defense": 1000, "magic_defense": 80, "attack_range": 300, "attack_speed": 60, "attack_wait": 30, "attack_interval": 161, "move_speed": 250.0, "dot_rate": 2.0, "assassin_resist": 1, "transform_resist": 1, "pattern_id": 2103776, "race_id": 2, "change_to": 15, "change_condition": 2, "missile_id": 39, "missile": {"splash": 133}, "master_id": 31575, "global_id": 5194, "ranged": true, "to_condition": 2, "to_global_id": 5195}, {"enemy_id": 14, "source": "local", "count": 1, "form_index": 2, "form_count": 3, "hp": 27000, "attack": 750, "base_hp": 27000, "base_attack": 750, "damage_type": "magical", "armor_defense": 1500, "magic_defense": 80, "attack_range": 68, "attack_speed": 60, "attack_wait": 10, "attack_interval": 121, "move_speed": 250.0, "gain_cost": 3, "dot_rate": 2.0, "assassin_resist": 1, "transform_resist": 100, "pattern_id": 2103792, "race_id": 2, "missile_id": 39, "missile": {"splash": 133}, "master_id": 31576, "global_id": 5195, "ranged": true, "from_condition": 2}, {"enemy_id": 17, "source": "local", "count": 2, "form_count": 3, "hp": 6000, "base_hp": 6000, "damage_type": "magical", "armor_defense": 600, "magic_defense": 80, "attack_speed": 60, "attack_wait": 30, "attack_interval": 221, "move_speed": 250.0, "dot_rate": 1.600000023841858, "assassin_resist": 100, "transform_resist": 100, "pattern_id": 2103776, "race_id": 2, "change_to": 17, "missile_id": 39, "missile": {"splash": 133}, "master_id": 30283, "global_id": 3902, "to_global_id": 476, "route_behaviour": {"transforms": [{}]}, "spawn_sec": 180}, {"enemy_id": 17, "source": "local", "count": 1, "form_index": 1, "form_count": 3, "hp": 6000, "attack": 300, "base_hp": 6000, "base_attack": 300, "damage_type": "magical", "armor_defense": 600, "magic_defense": 80, "attack_range": 400, "attack_speed": 60, "attack_wait": 30, "attack_interval": 161, "move_speed": 250.0, "dot_rate": 1.600000023841858, "assassin_resist": 100, "transform_resist": 100, "pattern_id": 2103776, "race_id": 2, "change_to": 18, "change_condition": 2, "missile_id": 39, "missile": {"splash": 133}, "master_id": 477, "global_id": 476, "ranged": true, "to_condition": 2, "to_global_id": 477}, {"enemy_id": 17, "source": "local", "count": 1, "form_index": 2, "form_count": 3, "hp": 16000, "attack": 450, "base_hp": 16000, "base_attack": 450, "damage_type": "magical", "armor_defense": 900, "magic_defense": 80, "attack_range": 90, "attack_speed": 60, "attack_wait": 10, "attack_interval": 121, "move_speed": 200.0, "gain_cost": 3, "dot_rate": 1.600000023841858, "assassin_resist": 100, "transform_resist": 100, "pattern_id": 2103792, "race_id": 2, "missile_id": 39, "missile": {"splash": 133}, "master_id": 478, "global_id": 477, "ranged": true, "from_condition": 2}], "popups": ["緑のオーブの装置がある間、\n全ての敵、装置のHPが\n徐々に回復します。\n\n装置は撃破数に含まれません。"], "active": true}