{"quest_id": 3438, "name": "蠱惑の彼岸花", "description": "堕姫の誘惑の術、そして王妃人との連携で\n敵方を翻弄し、砦の防衛演習に勝利せよ！\n%c[ff4000]選択した覚醒ユニットと王子、\n固定メンバーで出撃します。%c[ffffff]", "event": "交流クエスト", "event_category": "Harlem", "mission_id": 600001, "map_no": 6041, "entry_no": 5, "level": 100, "multiplier": 1.0, "charisma": 25, "capacity": 8, "enemies": [{"enemy_id": 1, "source": "local", "count": 8, "form_count": 1, "hp": 1200, "attack": 150, "base_hp": 1200, "base_attack": 150, "damage_type": "physical", "armor_defense": 400, "magic_defense": 5, "attack_speed": 80, "attack_wait": 60, "attack_interval": 270, "move_speed": 1600.0, "gain_cost": 1, "dot_rate": 1.5, "assassin_resist": 1000, "transform_resist": 1000, "pattern_id": 2097776, "race_id": 16, "master_id": 34, "global_id": 33, "spawn_sec": 1}, {"enemy_id": 7, "source": "local", "count": 8, "form_count": 1, "hp": 1500, "attack": 300, "base_hp": 1500, "base_attack": 300, "damage_type": "physical", "armor_defense": 50, "attack_speed": 70, "attack_wait": 10, "attack_interval": 131, "move_speed": 600.0, "gain_cost": 1, "dot_rate": 1.5, "assassin_resist": 1000, "transform_resist": 1000, "pattern_id": 2097488, "race_id": 16, "master_id": 25, "global_id": 24, "spawn_sec": 8}, {"enemy_id": 8, "source": "local", "count": 13, "form_count": 1, "tags": ["アーマー"], "hp": 3000, "attack": 500, "base_hp": 3000, "base_attack": 500, "damage_type": "physical", "armor_defense": 300, "attack_speed": 70, "attack_wait": 10, "attack_interval": 172, "move_speed": 450.0, "gain_cost": 1, "dot_rate": 1.399999976158142, "assassin_resist": 1000, "transform_resist": 1000, "pattern_id": 2097504, "race_id": 16, "master_id": 26, "global_id": 25, "spawn_sec": 48}, {"enemy_id": 2, "source": "local", "count": 8, "form_count": 1, "hp": 1500, "attack": 500, "base_hp": 1500, "base_attack": 500, "damage_type": "physical", "armor_defense": 80, "magic_defense": 20, "attack_range": 40, "attack_speed": 60, "attack_wait": 10, "attack_interval": 51, "move_speed": 1100.0, "gain_cost": 1, "dot_rate": 1.5, "assassin_resist": 1000, "transform_resist": 1000, "pattern_id": 2099776, "race_id": 16, "missile_id": 45, "master_id": 240, "global_id": 239, "ranged": true, "spawn_sec": 66}, {"enemy_id": 3, "source": "local", "count": 6, "form_count": 1, "hp": 2500, "attack": 600, "base_hp": 2500, "base_attack": 600, "damage_type": "physical", "armor_defense": 200, "magic_defense": 5, "attack_speed": 70, "attack_wait": 10, "attack_interval": 160, "move_speed": 1600.0, "gain_cost": 1, "dot_rate": 1.5, "assassin_resist": 1000, "transform_resist": 1000, "pattern_id": 2097520, "race_id": 16, "master_id": 27, "global_id": 26, "spawn_sec": 121}, {"enemy_id": 5, "source": "local", "count": 1, "level": 130, "form_count": 1, "hp": 15000, "attack": 1200, "base_hp": 15000, "base_attack": 1200, "damage_type": "physical", "armor_defense": 250, "magic_defense": 20, "attack_speed": 60, "attack_wait": 10, "attack_interval": 150, "move_speed": 1700.0, "gain_cost": 3, "dot_rate": 1.5, "assassin_resist": 100, "transform_resist": 100, "pattern_id": 2097904, "race_id": 16, "special_effect_id": 222, "master_id": 58, "global_id": 57, "spawn_sec": 135}], "active": true}