{"quest_id": 8268, "name": "階層を超えた交流", "description": "宴のフィナーレで磨き上げた技を披露せよ！\n＜天界（弱）：攻撃力がダウン。\n　一部を除く敵味方のＨＰが徐々に回復＞\n神級EX（★１獲得の目安：平均覚醒Lv25）", "modifier_notes": ["天界（弱）：攻撃力がダウン。\n　一部を除く敵味方のＨＰが徐々に回復"], "event": "人気闘兵凱旋パレードIV", "event_category": "History", "mission_id": 920215, "map_no": 4905, "level": 100, "multiplier": 1.0, "charisma": 150, "capacity": 8, "modifiers": [{"kind": "term", "influence": 45, "params": [100, -70]}, {"kind": "term", "influence": 41, "params": [0, 60, 30], "expression": "(IsIdentitiy(\"アンデッド\") || IsRace(\"デーモン\")) == 0;", "expression_human": "not (it has the identity アンデッド or its race is デーモン)"}, {"kind": "term", "influence": 29, "params": [0, 10, 30], "expression": "(IsIdentitiy(\"アンデッド\") || IsRace(\"デーモン\")) == 0;", "expression_human": "not (it has the identity アンデッド or its race is デーモン)"}], "enemies": [{"enemy_id": 1, "source": "local", "count": 1, "form_count": 1, "hp": 98000, "attack": 2400, "base_hp": 98000, "base_attack": 2400, "damage_type": "physical", "armor_defense": 350, "magic_defense": 30, "attack_range": 280, "attack_speed": 55, "attack_wait": 40, "attack_interval": 121, "move_speed": 500.0, "gain_cost": 2, "dot_rate": 1.5, "assassin_resist": 1, "transform_resist": 100, "pattern_id": 2153120, "race_id": 6, "special_effect_id": 267, "missile_id": 22, "missile": {"speed": 10.0}, "master_id": 37448, "global_id": 11065, "ranged": true, "spawn_sec": 41}, {"enemy_id": 2, "source": "local", "count": 1, "form_count": 1, "hp": 100000, "attack": 2000, "base_hp": 100000, "base_attack": 2000, "damage_type": "magical", "armor_defense": 300, "magic_defense": 30, "attack_range": 260, "attack_wait": 25, "attack_interval": 87, "move_speed": 600.0, "gain_cost": 3, "dot_rate": 1.5, "assassin_resist": 1, "transform_resist": 100, "pattern_id": 2148080, "race_id": 19, "special_effect_id": 1552, "missile_id": 22, "missile": {"speed": 10.0}, "master_id": 37474, "global_id": 11091, "ranged": true, "spawn_sec": 41}, {"enemy_id": 3, "source": "local", "count": 1, "form_count": 1, "hp": 104000, "attack": 1000, "base_hp": 104000, "base_attack": 1000, "damage_type": "magical", "armor_defense": 3000, "magic_defense": 30, "attack_speed": 10, "attack_wait": 60, "attack_interval": 176, "move_speed": 700.0, "gain_cost": 3, "dot_rate": 1.5, "assassin_resist": 1, "transform_resist": 100, "pattern_id": 2153104, "race_id": 4, "special_effect_id": 1718, "master_id": 37447, "global_id": 11064, "spawn_sec": 41}, {"enemy_id": 4, "source": "local", "count": 1, "form_count": 1, "hp": 92000, "attack": 1000, "base_hp": 92000, "base_attack": 1000, "damage_type": "magical", "armor_defense": 300, "magic_defense": 20, "attack_range": 280, "attack_speed": 100, "attack_wait": 20, "attack_interval": 60, "move_speed": 450.0, "gain_cost": 3, "dot_rate": 1.5, "assassin_resist": 1, "transform_resist": 1, "pattern_id": 2143696, "special_effect_id": 1301, "missile_id": 45, "master_id": 36052, "global_id": 9669, "ranged": true, "spawn_sec": 41}, {"enemy_id": 5, "source": "local", "count": 1, "form_count": 1, "hp": 68000, "attack": 3000, "base_hp": 68000, "base_attack": 3000, "damage_type": "physical", "armor_defense": 300, "magic_defense": 20, "attack_range": 240, "attack_speed": 20, "attack_wait": 70, "attack_interval": 193, "move_speed": 600.0, "gain_cost": 3, "dot_rate": 1.5, "assassin_resist": 1, "transform_resist": 100, "pattern_id": 2145776, "race_id": 19, "special_effect_id": 1433, "missile_id": 560, "missile": {"speed": 6.0}, "master_id": 37471, "global_id": 11088, "ranged": true, "spawn_sec": 128}, {"enemy_id": 6, "source": "local", "count": 1, "form_count": 1, "hp": 72000, "attack": 3800, "base_hp": 72000, "base_attack": 3800, "damage_type": "magical", "armor_defense": 250, "magic_defense": 20, "attack_range": 100, "attack_speed": 1, "attack_wait": 90, "attack_interval": 235, "move_speed": 600.0, "gain_cost": 3, "dot_rate": 1.5, "assassin_resist": 1, "transform_resist": 100, "pattern_id": 2145760, "race_id": 19, "special_effect_id": 1039, "missile_id": 7, "missile": {"speed": 6.0, "splash": 133}, "master_id": 37470, "global_id": 11087, "ranged": true, "spawn_sec": 129}, {"enemy_id": 7, "source": "local", "count": 10, "form_count": 1, "hp": 2800, "attack": 200, "base_hp": 2800, "base_attack": 200, "damage_type": "physical", "armor_defense": 40, "attack_speed": 1, "attack_wait": 1, "attack_interval": 20, "move_speed": 1600.0, "gain_cost": 2, "dot_rate": 1.5, "assassin_resist": 100, "transform_resist": 100, "pattern_id": 2145712, "race_id": 12, "special_effect_id": 621, "master_id": 36329, "global_id": 9946, "spawn_sec": 171}, {"enemy_id": 8, "source": "local", "count": 4, "form_count": 1, "hp": 3200, "attack": 750, "base_hp": 3200, "base_attack": 750, "damage_type": "physical", "armor_defense": 400, "attack_speed": 70, "attack_wait": 90, "attack_interval": 335, "move_speed": 400.0, "gain_cost": 1, "dot_rate": 1.2999999523162842, "assassin_resist": 1000, "transform_resist": 1000, "pattern_id": 2145696, "race_id": 12, "master_id": 36328, "global_id": 9945, "spawn_sec": 182}, {"enemy_id": 9, "source": "local", "count": 4, "form_count": 1, "tags": ["アンデッド"], "hp": 12000, "attack": 260, "base_hp": 12000, "base_attack": 260, "damage_type": "physical", "armor_defense": 210, "magic_defense": 30, "attack_range": 100, "attack_speed": 70, "attack_wait": 30, "attack_interval": 93, "move_speed": 300.0, "gain_cost": 1, "dot_rate": 1.5, "assassin_resist": 100, "transform_resist": 100, "pattern_id": 2112048, "race_id": 12, "special_effect_id": 193, "missile_id": 45, "master_id": 30641, "global_id": 4260, "ranged": true, "spawn_sec": 187}, {"enemy_id": 10, "source": "local", "count": 4, "form_count": 1, "tags": ["アンデッド"], "hp": 20000, "attack": 1000, "base_hp": 20000, "base_attack": 1000, "damage_type": "physical", "armor_defense": 500, "attack_speed": 70, "attack_wait": 80, "attack_interval": 309, "move_speed": 400.0, "gain_cost": 1, "dot_rate": 1.2999999523162842, "assassin_resist": 1000, "transform_resist": 1000, "pattern_id": 2145824, "race_id": 12, "special_effect_id": 227, "master_id": 36338, "global_id": 9955, "spawn_sec": 198}, {"enemy_id": 11, "source": "local", "count": 1, "form_count": 1, "tags": ["ヒュープ"], "hp": 140000, "base_hp": 140000, "damage_type": "physical", "armor_defense": 250, "magic_defense": 30, "attack_wait": 60, "attack_interval": 169, "move_speed": 600.0, "gain_cost": 3, "dot_rate": 1.5, "transform_resist": 1, "pattern_id": 2138944, "race_id": 19, "special_effect_id": 1102, "master_id": 35116, "global_id": 8733, "commands": {"raw": "SetStageFlag(0, 0);", "sets_flags": [[0, 0]]}, "route_behaviour": {"sets_flags": [[0, 1, 0]]}, "spawn_sec": 225}, {"enemy_id": 12, "source": "local", "count": 1, "form_count": 1, "tags": ["置物", "ステルスII", "ブロック不可"], "fixture": true, "hp": 50000, "base_hp": 50000, "damage_type": "physical", "attack_wait": 60, "attack_interval": 169, "move_speed": 1200.0, "gain_cost": 3, "dot_rate": 1.5, "pattern_id": 2138928, "special_effect_id": 1103, "master_id": 35117, "global_id": 8734, "commands": {"raw": "SetStageFlag(1, 0); SetStageFlag(2, 1); SetStageFlag(3, 1); SetStageFlag(4, 1); SetStageFlag(5, 1); SetStageFlag(6, 1); SetStageFlag(7, 1); SetStageFlag(8, 1); SetStageFlag(9, 1); SetStageFlag(10, 1); SetStageFlag(11, 1); SetStageFlag(12, 1);", "sets_flags": [[1, 0], [2, 1], [3, 1], [4, 1], [5, 1], [6, 1], [7, 1], [8, 1], [9, 1], [10, 1], [11, 1], [12, 1]]}, "route_behaviour": {"reroutes": ["Route=999"]}, "spawn_sec": 225}, {"enemy_id": 13, "source": "local", "count": 20, "form_count": 1, "hp": 3500, "attack": 500, "base_hp": 3500, "base_attack": 500, "damage_type": "physical", "armor_defense": 50, "magic_defense": 20, "attack_speed": 1, "attack_wait": 40, "attack_interval": 122, "move_speed": 600.0, "gain_cost": 2, "dot_rate": 1.5, "assassin_resist": 100, "transform_resist": 100, "pattern_id": 2138880, "race_id": 16, "special_effect_id": 1100, "master_id": 35114, "global_id": 8731, "spawn_sec": 357}, {"enemy_id": 14, "source": "local", "count": 3, "form_count": 1, "hp": 6000, "attack": 500, "base_hp": 6000, "base_attack": 500, "damage_type": "physical", "armor_defense": 20, "magic_defense": 5, "attack_range": 2000, "attack_speed": 1, "attack_wait": 90, "attack_interval": 229, "move_speed": 1200.0, "gain_cost": 1, "dot_rate": 1.5, "pattern_id": 2138928, "special_effect_id": 1101, "missile_id": 560, "missile": {"speed": 6.0}, "master_id": 35115, "global_id": 8732, "ranged": true, "spawn_sec": 363}, {"enemy_id": 15, "source": "local", "count": 1, "form_count": 1, "tags": ["置物", "ステルスII", "ブロック不可"], "fixture": true, "hp": 50000, "base_hp": 50000, "damage_type": "physical", "attack_wait": 60, "attack_interval": 169, "move_speed": 1200.0, "gain_cost": 3, "dot_rate": 1.5, "pattern_id": 2138928, "special_effect_id": 1104, "master_id": 35118, "global_id": 8735, "commands": {"raw": "SetStageFlag(2, 0);", "sets_flags": [[2, 0]]}, "route_behaviour": {"reroutes": ["Route=998"]}, "spawn_sec": 369}, {"enemy_id": 16, "source": "local", "count": 1, "form_count": 1, "tags": ["置物", "ステルスII", "ブロック不可"], "fixture": true, "hp": 50000, "base_hp": 50000, "damage_type": "physical", "attack_wait": 60, "attack_interval": 169, "move_speed": 1200.0, "gain_cost": 3, "dot_rate": 1.5, "pattern_id": 2138928, "special_effect_id": 1105, "master_id": 35119, "global_id": 8736, "commands": {"raw": "SetStageFlag(3, 0);", "sets_flags": [[3, 0]]}, "route_behaviour": {"reroutes": ["Route=998"]}, "spawn_sec": 382}, {"enemy_id": 17, "source": "local", "count": 1, "form_count": 2, "hp": 88000, "attack": 1800, "base_hp": 88000, "base_attack": 1800, "damage_type": "physical", "armor_defense": 500, "attack_range": 320, "attack_speed": 70, "attack_wait": 120, "attack_interval": 313, "move_speed": 450.0, "gain_cost": 3, "dot_rate": 1.5, "assassin_resist": 1, "transform_resist": 1, "pattern_id": 2144720, "race_id": 19, "special_effect_id": 1391, "change_to": 17, "missile_id": 192, "missile": {"speed": 4.0, "splash": 144}, "master_id": 37472, "global_id": 11089, "ranged": true, "to_global_id": 11090, "spawn_sec": 393}, {"enemy_id": 17, "source": "local", "count": 1, "form_index": 1, "form_count": 2, "hp": 88000, "attack": 1800, "base_hp": 88000, "base_attack": 1800, "damage_type": "physical", "armor_defense": 500, "attack_range": 320, "attack_speed": 70, "attack_wait": 120, "attack_interval": 313, "move_speed": 450.0, "gain_cost": 3, "dot_rate": 1.5, "assassin_resist": 1, "transform_resist": 1, "pattern_id": 2144720, "race_id": 19, "special_effect_id": 1392, "change_to": 16, "missile_id": 192, "missile": {"speed": 4.0, "splash": 144}, "master_id": 37473, "global_id": 11090, "ranged": true}, {"enemy_id": 19, "source": "local", "count": 1, "form_count": 1, "tags": ["置物", "ステルスII", "ブロック不可"], "fixture": true, "hp": 50000, "base_hp": 50000, "damage_type": "physical", "attack_wait": 60, "attack_interval": 169, "move_speed": 1200.0, "gain_cost": 3, "dot_rate": 1.5, "pattern_id": 2138928, "special_effect_id": 1106, "master_id": 35120, "global_id": 8737, "commands": {"raw": "SetStageFlag(4, 0);", "sets_flags": [[4, 0]]}, "route_behaviour": {"reroutes": ["Route=998"]}, "spawn_sec": 470}, {"enemy_id": 20, "source": "local", "count": 1, "form_count": 1, "tags": ["置物", "ステルスII", "ブロック不可"], "fixture": true, "hp": 50000, "base_hp": 50000, "damage_type": "physical", "attack_wait": 60, "attack_interval": 169, "move_speed": 1200.0, "gain_cost": 3, "dot_rate": 1.5, "pattern_id": 2138928, "special_effect_id": 1107, "master_id": 35121, "global_id": 8738, "commands": {"raw": "SetStageFlag(5, 0);", "sets_flags": [[5, 0]]}, "route_behaviour": {"reroutes": ["Route=998"]}, "spawn_sec": 483}, {"enemy_id": 21, "source": "local", "count": 20, "form_count": 1, "hp": 4800, "attack": 800, "base_hp": 4800, "base_attack": 800, "damage_type": "physical", "armor_defense": 80, "magic_defense": 20, "attack_speed": 1, "attack_wait": 60, "attack_interval": 170, "move_speed": 600.0, "gain_cost": 2, "dot_rate": 1.5, "assassin_resist": 100, "transform_resist": 100, "pattern_id": 2138896, "race_id": 11, "special_effect_id": 1100, "master_id": 35113, "global_id": 8730, "spawn_sec": 489}, {"enemy_id": 22, "source": "local", "count": 1, "form_count": 1, "tags": ["置物", "ステルスII", "ブロック不可"], "fixture": true, "hp": 50000, "base_hp": 50000, "damage_type": "physical", "attack_wait": 60, "attack_interval": 169, "move_speed": 1200.0, "gain_cost": 3, "dot_rate": 1.5, "pattern_id": 2138928, "special_effect_id": 1108, "master_id": 35122, "global_id": 8739, "commands": {"raw": "SetStageFlag(6, 0);", "sets_flags": [[6, 0]]}, "route_behaviour": {"reroutes": ["Route=998"]}, "spawn_sec": 497}, {"enemy_id": 23, "source": "local", "count": 8, "form_count": 1, "tags": ["鳥"], "hp": 2000, "base_hp": 2000, "damage_type": "physical", "armor_defense": 30, "magic_defense": 5, "attack_speed": 1, "move_speed": 1400.0, "gain_cost": 1, "dot_rate": 1.2000000476837158, "assassin_resist": 1000, "transform_resist": 1000, "pattern_id": 2144624, "race_id": 11, "master_id": 36232, "global_id": 9849, "spawn_sec": 497}, {"enemy_id": 24, "source": "local", "count": 6, "form_count": 2, "hp": 7500, "base_hp": 7500, "damage_type": "magical", "armor_defense": 100, "magic_defense": 5, "attack_speed": 70, "attack_wait": 70, "attack_interval": 261, "move_speed": 450.0, "gain_cost": 1, "dot_rate": 1.5, "assassin_resist": 100, "transform_resist": 100, "pattern_id": 2144656, "race_id": 11, "special_effect_id": 1179, "change_to": 24, "change_condition": 5, "master_id": 36234, "global_id": 9851, "to_condition": 5, "to_global_id": 9852, "spawn_sec": 502}, {"enemy_id": 24, "source": "local", "count": 1, "form_index": 1, "form_count": 2, "hp": 7500, "attack": 700, "base_hp": 7500, "base_attack": 700, "damage_type": "magical", "armor_defense": 100, "magic_defense": 5, "attack_range": 300, "attack_speed": 70, "attack_wait": 70, "attack_interval": 191, "move_speed": 450.0, "gain_cost": 1, "dot_rate": 1.5, "assassin_resist": 100, "transform_resist": 100, "pattern_id": 2144672, "race_id": 11, "missile_id": 85, "missile": {"slow": [99, 0]}, "master_id": 36235, "global_id": 9852, "ranged": true, "from_condition": 5}, {"enemy_id": 26, "source": "local", "count": 1, "form_count": 1, "tags": ["置物", "ステルスII", "ブロック不可"], "fixture": true, "hp": 50000, "base_hp": 50000, "damage_type": "physical", "attack_wait": 60, "attack_interval": 169, "move_speed": 1200.0, "gain_cost": 3, "dot_rate": 1.5, "pattern_id": 2138928, "special_effect_id": 1109, "master_id": 35123, "global_id": 8740, "commands": {"raw": "SetStageFlag(7, 0);", "sets_flags": [[7, 0]]}, "route_behaviour": {"reroutes": ["Route=998"]}, "spawn_sec": 548}, {"enemy_id": 27, "source": "local", "count": 1, "form_count": 1, "tags": ["置物", "ステルスII", "ブロック不可"], "fixture": true, "hp": 50000, "base_hp": 50000, "damage_type": "physical", "attack_wait": 60, "attack_interval": 169, "move_speed": 1200.0, "gain_cost": 3, "dot_rate": 1.5, "pattern_id": 2138928, "special_effect_id": 1110, "master_id": 35124, "global_id": 8741, "commands": {"raw": "SetStageFlag(8, 0);", "sets_flags": [[8, 0]]}, "route_behaviour": {"reroutes": ["Route=998"]}, "spawn_sec": 561}, {"enemy_id": 28, "source": "local", "count": 4, "form_count": 2, "hp": 15000, "base_hp": 15000, "damage_type": "magical", "armor_defense": 400, "magic_defense": 10, "attack_speed": 70, "attack_wait": 70, "attack_interval": 261, "move_speed": 450.0, "gain_cost": 1, "dot_rate": 1.5, "assassin_resist": 100, "transform_resist": 100, "pattern_id": 2144688, "race_id": 11, "special_effect_id": 1179, "change_to": 28, "change_condition": 5, "master_id": 36236, "global_id": 9853, "to_condition": 5, "to_global_id": 9854, "spawn_sec": 564}, {"enemy_id": 28, "source": "local", "count": 1, "form_index": 1, "form_count": 2, "hp": 15000, "attack": 1800, "base_hp": 15000, "base_attack": 1800, "damage_type": "magical", "armor_defense": 400, "magic_defense": 10, "attack_range": 300, "attack_speed": 70, "attack_wait": 70, "attack_interval": 201, "move_speed": 450.0, "gain_cost": 1, "dot_rate": 1.5, "assassin_resist": 100, "transform_resist": 100, "pattern_id": 2144704, "race_id": 11, "missile_id": 85, "missile": {"slow": [99, 0]}, "master_id": 36237, "global_id": 9854, "ranged": true, "from_condition": 5}, {"enemy_id": 30, "source": "local", "count": 1, "form_count": 1, "hp": 23000, "attack": 800, "base_hp": 23000, "base_attack": 800, "damage_type": "magical", "armor_defense": 400, "magic_defense": 25, "attack_range": 240, "attack_speed": 70, "attack_wait": 35, "attack_interval": 101, "move_speed": 300.0, "gain_cost": 3, "dot_rate": 1.5, "assassin_resist": 1, "transform_resist": 100, "pattern_id": 2112688, "race_id": 6, "missile_id": 236, "missile": {"speed": 8.0}, "master_id": 30714, "global_id": 4333, "ranged": true, "spawn_sec": 574}, {"enemy_id": 31, "source": "local", "count": 1, "form_count": 1, "hp": 45000, "attack": 800, "base_hp": 45000, "base_attack": 800, "damage_type": "magical", "armor_defense": 400, "magic_defense": 30, "attack_range": 300, "attack_speed": 70, "attack_wait": 35, "attack_interval": 130, "move_speed": 300.0, "gain_cost": 3, "dot_rate": 1.5, "assassin_resist": 1, "transform_resist": 100, "pattern_id": 2111712, "race_id": 6, "missile_id": 229, "missile": {"speed": 6.0, "splash": 133}, "master_id": 30625, "global_id": 4244, "ranged": true, "spawn_sec": 574}, {"enemy_id": 32, "source": "local", "count": 1, "form_count": 1, "tags": ["置物", "ステルスII", "ブロック不可"], "fixture": true, "hp": 50000, "base_hp": 50000, "damage_type": "physical", "attack_wait": 60, "attack_interval": 169, "move_speed": 1200.0, "gain_cost": 3, "dot_rate": 1.5, "pattern_id": 2138928, "special_effect_id": 1111, "master_id": 35125, "global_id": 8742, "commands": {"raw": "SetStageFlag(9, 0);", "sets_flags": [[9, 0]]}, "route_behaviour": {"reroutes": ["Route=998"]}, "spawn_sec": 575}, {"enemy_id": 33, "source": "local", "count": 1, "form_count": 1, "hp": 25000, "attack": 1400, "base_hp": 25000, "base_attack": 1400, "damage_type": "physical", "armor_defense": 300, "magic_defense": 25, "attack_range": 400, "attack_speed": 70, "attack_wait": 35, "attack_interval": 130, "move_speed": 300.0, "gain_cost": 3, "dot_rate": 1.5, "assassin_resist": 1, "transform_resist": 100, "pattern_id": 2105472, "race_id": 6, "special_effect_id": 73, "missile_id": 151, "missile": {"speed": 3.0}, "master_id": 33830, "global_id": 7447, "ranged": true, "spawn_sec": 576}, {"enemy_id": 34, "source": "local", "count": 1, "form_count": 1, "hp": 26000, "attack": 800, "base_hp": 26000, "base_attack": 800, "damage_type": "magical", "armor_defense": 1000, "magic_defense": 30, "attack_range": 300, "attack_speed": 70, "attack_wait": 70, "attack_interval": 171, "move_speed": 600.0, "gain_cost": 3, "dot_rate": 1.5, "assassin_resist": 1, "transform_resist": 100, "pattern_id": 2143968, "race_id": 6, "special_effect_id": 1310, "missile_id": 22, "missile": {"speed": 10.0}, "master_id": 36124, "global_id": 9741, "ranged": true, "spawn_sec": 576}, {"enemy_id": 35, "source": "local", "count": 8, "form_count": 1, "tags": ["鳥"], "hp": 8000, "base_hp": 8000, "damage_type": "physical", "armor_defense": 250, "magic_defense": 10, "attack_speed": 1, "move_speed": 1400.0, "gain_cost": 2, "dot_rate": 1.2000000476837158, "assassin_resist": 1000, "transform_resist": 1000, "pattern_id": 2144640, "race_id": 11, "master_id": 36233, "global_id": 9850, "spawn_sec": 589}, {"enemy_id": 36, "source": "local", "count": 1, "form_count": 1, "tags": ["置物", "ステルスII", "ブロック不可"], "fixture": true, "hp": 50000, "base_hp": 50000, "damage_type": "physical", "attack_wait": 60, "attack_interval": 169, "move_speed": 1200.0, "gain_cost": 3, "dot_rate": 1.5, "pattern_id": 2138928, "special_effect_id": 1112, "master_id": 35126, "global_id": 8743, "commands": {"raw": "SetStageFlag(10, 0);", "sets_flags": [[10, 0]]}, "route_behaviour": {"reroutes": ["Route=998"]}, "spawn_sec": 591}, {"enemy_id": 37, "source": "local", "count": 1, "form_count": 1, "tags": ["置物", "ステルスII", "ブロック不可"], "fixture": true, "hp": 50000, "base_hp": 50000, "damage_type": "physical", "attack_wait": 60, "attack_interval": 169, "move_speed": 1200.0, "gain_cost": 3, "dot_rate": 1.5, "pattern_id": 2138928, "special_effect_id": 1113, "master_id": 35127, "global_id": 8744, "commands": {"raw": "SetStageFlag(11, 0);", "sets_flags": [[11, 0]]}, "route_behaviour": {"reroutes": ["Route=998"]}, "spawn_sec": 604}], "popups": ["\n\n\n　　　　　――天界", "クロノシアは一定確率で\n物理攻撃を回避します。\n\nまたクロノシアは自身が受けた\n停止の効果を無効化します。", "カゴメは攻撃を受けると\n受けたダメージの50%のダメージで\n攻撃したユニットへ反撃を行います。", "ゼクメトがいる間\n全ての敵のHPが徐々に回復します。", "亜神ヒュープは攻撃を行いませんが、\n亜神ヒュープがいる間は\n味方の攻撃、防御がダウンします。\n\nまた一定時間が経過するたびに\nステータスダウン効果が強化され\n最大90％までダウンします。", "亜神ヒュープの眷属(人型)は\n倒されると自身の周囲に\nダメージを与えます。", "亜神ヒュープの眷属(羊型)は\n倒されると自身の周囲に\nダメージを与えます。", "亜神ヒュープの眷属(泡沫型)が\nいる間は、全ての敵のHPが\n徐々に回復します。\n\nまた亜神ヒュープの眷属(泡沫型)は\n攻撃を行いません。", "敵にハリンヘイムがいる間は\n全ての敵の攻撃力が\nアップします。\n\nまたハリンヘイムがいる間は\n全ての味方ユニットの\n防御力が低下します。", "ハリンヘイムが味方ユニットの\n射程範囲内にいる場合、\n遠距離攻撃を自身に引き付けます。\n\nスキルやアビリティなどで\n攻撃の優先順位が指定された\n敵がいる場合や一部の攻撃は\n引き付けの効果を受けません。", "エイクシュニルのHPを減らすと、\n遠距離攻撃をしてきます。"], "active": true}