{"quest_id": 8416, "name": "超極級", "description": "大神ディアスを撃破せよ！\n\n＜編成内での同ユニット禁止＞\n%c[ff4000]＜ユニット、アイテムのドロップなし＞%c[ffffff]", "modifier_notes": ["編成内での同ユニット禁止", "ユニット、アイテムのドロップなし"], "event": "大神降臨真ディアス", "event_category": "Devil Advent", "mission_id": 500476, "map_no": 5071, "level": 320, "multiplier": 3.2, "charisma": 25, "capacity": 10, "modifiers": [{"kind": "term", "influence": 24, "params": [10], "expression": "IsOverlapMember() != 1;", "expression_human": "it is not a duplicate of another unit in your team"}], "enemies": [{"enemy_id": 1, "source": "local", "count": 1, "form_count": 2, "tags": ["置物", "ステルスII", "ブロック不可"], "fixture": true, "hp": 576000, "base_hp": 180000, "damage_type": "physical", "armor_defense": 1800, "magic_defense": 60, "attack_speed": 1, "attack_wait": 60, "attack_interval": 182, "move_speed": 300.0, "gain_cost": 3, "dot_rate": 1.5, "pattern_id": 2156992, "change_to": 1, "master_id": 38052, "global_id": 11669, "to_global_id": 11644, "commands": {"raw": "DoEnemy_Performance(\"ENBSTL_NoAttack\");"}, "route_behaviour": {"transforms": [{}], "reroutes": ["Route=913"]}}, {"enemy_id": 1, "source": "local", "count": 1, "form_index": 1, "form_count": 2, "tags": ["置物", "ブロック不可"], "fixture": true, "hp": 576000, "base_hp": 180000, "damage_type": "physical", "armor_defense": 1800, "magic_defense": 60, "attack_speed": 1, "attack_wait": 60, "attack_interval": 182, "move_speed": 300.0, "gain_cost": 3, "dot_rate": 1.5, "pattern_id": 2156992, "special_effect_id": 1886, "master_id": 38027, "global_id": 11644}, {"enemy_id": 3, "source": "local", "count": 1, "form_count": 1, "tags": ["水中"], "hp": 496000, "attack": 3500, "base_hp": 155000, "base_attack": 3500, "damage_type": "physical", "armor_defense": 1200, "magic_defense": 60, "attack_range": 80, "attack_interval": 79, "move_speed": 200.0, "gain_cost": 3, "dot_rate": 1.5, "assassin_resist": 1, "transform_resist": 100, "pattern_id": 2123664, "race_id": 6, "special_effect_id": 553, "missile_id": 45, "master_id": 21805, "global_id": 2088, "ranged": true, "commands": {"raw": "DoEnemy_RegistCommand(\"OnDestroy\", \"SetStageFlag(1, 1, 127);\");", "sets_flags": [[1, 1]], "on_destroy": true}}, {"enemy_id": 4, "source": "local", "count": 1, "form_count": 6, "tags": ["置物", "ステルスII", "ブロック不可"], "fixture": true, "hp": 384000, "attack": 9600, "base_hp": 120000, "base_attack": 3000, "damage_type": "physical", "armor_defense": 1500, "magic_defense": 60, "attack_speed": 1, "attack_wait": 90, "attack_interval": 242, "move_speed": 300.0, "gain_cost": 3, "dot_rate": 1.5, "pattern_id": 2157008, "change_to": 4, "master_id": 38053, "global_id": 11670, "to_global_id": 11647, "commands": {"raw": "DoEnemy_Performance(\"ENBSTL_NoAttack\"); FlagCheckCommandOrder(118, 1, 127, 1, \"DoEnemy_ModeChange();\"); FlagCheckCommandOrder(119, 1, 127, 1, \"DoEnemy_ModeChange();\"); FlagCheckCommandOrder(120, 1, 127, 1, \"DoEnemy_ModeChange();\"); FlagCheckCommandOrder(121, 1, 127, 1, \"DoEnemy_ModeChange();\");", "mode_changes": 4, "flag_checks": ["118, 1, 127, 1, \"DoEnemy_ModeChange(", "119, 1, 127, 1, \"DoEnemy_ModeChange(", "120, 1, 127, 1, \"DoEnemy_ModeChange(", "121, 1, 127, 1, \"DoEnemy_ModeChange("]}, "route_behaviour": {"transforms": [{}], "reroutes": ["Route=923"]}}, {"enemy_id": 4, "source": "local", "count": 1, "form_index": 1, "form_count": 6, "tags": ["置物", "ブロック不可"], "fixture": true, "hp": 384000, "attack": 3000, "base_hp": 120000, "base_attack": 3000, "damage_type": "physical", "armor_defense": 1500, "magic_defense": 60, "attack_range": 400, "attack_speed": 1, "attack_wait": 90, "attack_interval": 241, "move_speed": 300.0, "gain_cost": 3, "dot_rate": 1.5, "pattern_id": 2157008, "special_effect_id": 1887, "change_to": 5, "missile_id": 208, "missile": {"speed": 5.0}, "master_id": 38030, "global_id": 11647, "ranged": true, "to_global_id": 11648}, {"enemy_id": 4, "source": "local", "count": 1, "form_index": 2, "form_count": 6, "tags": ["置物", "ブロック不可"], "fixture": true, "hp": 384000, "attack": 3000, "base_hp": 120000, "base_attack": 3000, "damage_type": "physical", "armor_defense": 1500, "magic_defense": 60, "attack_range": 400, "attack_speed": 1, "attack_wait": 75, "attack_interval": 211, "move_speed": 300.0, "gain_cost": 3, "dot_rate": 1.5, "pattern_id": 2157008, "special_effect_id": 1888, "change_to": 6, "missile_id": 208, "missile": {"speed": 5.0}, "master_id": 38031, "global_id": 11648, "ranged": true, "to_global_id": 11649}, {"enemy_id": 4, "source": "local", "count": 1, "form_index": 3, "form_count": 6, "tags": ["置物", "ブロック不可"], "fixture": true, "hp": 384000, "attack": 3000, "base_hp": 120000, "base_attack": 3000, "damage_type": "physical", "armor_defense": 1500, "magic_defense": 60, "attack_range": 400, "attack_speed": 1, "attack_wait": 50, "attack_interval": 161, "move_speed": 300.0, "gain_cost": 3, "dot_rate": 1.5, "pattern_id": 2157008, "special_effect_id": 1889, "change_to": 7, "missile_id": 208, "missile": {"speed": 5.0}, "master_id": 38032, "global_id": 11649, "ranged": true, "to_global_id": 11650}, {"enemy_id": 4, "source": "local", "count": 1, "form_index": 4, "form_count": 6, "tags": ["置物", "ブロック不可"], "fixture": true, "hp": 384000, "attack": 3000, "base_hp": 120000, "base_attack": 3000, "damage_type": "physical", "armor_defense": 1500, "magic_defense": 60, "attack_range": 400, "attack_speed": 1, "attack_wait": 25, "attack_interval": 111, "move_speed": 300.0, "gain_cost": 3, "dot_rate": 1.5, "pattern_id": 2157008, "special_effect_id": 1890, "change_to": 8, "missile_id": 208, "missile": {"speed": 5.0}, "master_id": 38033, "global_id": 11650, "ranged": true, "to_global_id": 11651}, {"enemy_id": 4, "source": "local", "count": 1, "form_index": 5, "form_count": 6, "tags": ["置物", "ブロック不可"], "fixture": true, "hp": 384000, "attack": 3000, "base_hp": 120000, "base_attack": 3000, "damage_type": "physical", "armor_defense": 1500, "magic_defense": 60, "attack_range": 400, "attack_speed": 1, "attack_wait": 1, "attack_interval": 63, "move_speed": 300.0, "gain_cost": 3, "dot_rate": 1.5, "pattern_id": 2157008, "special_effect_id": 1891, "missile_id": 208, "missile": {"speed": 5.0}, "master_id": 38034, "global_id": 11651, "ranged": true}, {"enemy_id": 10, "source": "local", "count": 5, "form_count": 1, "tags": ["ステルス", "置物"], "fixture": true, "hp": 3200, "attack": 3, "base_hp": 1000, "base_attack": 1, "damage_type": "physical", "armor_defense": 100, "attack_speed": 1, "attack_wait": 15, "attack_interval": 72, "move_speed": 1000.0, "gain_cost": 3, "dot_rate": 1.5, "assassin_resist": 1, "transform_resist": 1, "pattern_id": 2097200, "master_id": 33851, "global_id": 7468, "commands": {"raw": "DoEnemy_Performance(\"ENBSTL_NoAttack\");"}, "route_behaviour": {"sets_flags": [[112, 1, 1500], [113, 1, 1300], [114, 1, 1000], [115, 1, 700], [116, 1, 999999], [118, 1, 1200], [119, 1, 1200], [120, 1, 1200], [121, 1, 0], [4, 1, 60], [5, 1, 600], [6, 1, 60], [7, 1, 0], [8, 1, 60], [9, 1, 600], [10, 1, 60], [11, 1, 0], [12, 1, 60], [13, 1, 600], [14, 1, 60], [15, 1, 0], [16, 1, 60], [17, 1, 600], [18, 1, 60], [19, 1, 0], [20, 1, 60], [21, 1, 600], [22, 1, 60], [23, 1, 0], [24, 1, 60], [25, 1, 600], [26, 1, 60], [27, 1, 0], [28, 1, 60], [29, 1, 600], [30, 1, 60], [31, 1, 0], [32, 1, 60], [33, 1, 600], [34, 1, 60], [35, 1, 0], [36, 1, 60], [37, 1, 600], [38, 1, 60], [39, 1, 0], [40, 1, 60], [41, 1, 600], [42, 1, 60], [43, 1, 0], [44, 1, 60], [45, 1, 600], [46, 1, 60], [47, 1, 0], [48, 1, 60], [49, 1, 600], [50, 1, 60], [51, 1, 0], [52, 1, 60], [53, 1, 600], [54, 1, 60], [55, 1, 0], [56, 1, 60], [57, 1, 600], [58, 1, 60], [59, 1, 0], [60, 1, 60], [61, 1, 600], [62, 1, 60], [63, 1, 0], [64, 1, 60], [65, 1, 600], [66, 1, 60], [67, 1, 0], [68, 1, 60], [69, 1, 600], [70, 1, 60], [71, 1, 0], [72, 1, 60], [73, 1, 600], [74, 1, 60], [75, 1, 0], [76, 1, 60], [77, 1, 600], [78, 1, 60], [79, 1, 0], [80, 1, 60], [81, 1, 600], [82, 1, 60], [83, 1, 0], [84, 1, 60], [85, 1, 600], [86, 1, 60], [87, 1, 0], [88, 1, 60], [89, 1, 600], [90, 1, 60], [91, 1, 0], [92, 1, 60], [93, 1, 600], [94, 1, 60], [95, 1, 0], [96, 1, 60], [97, 1, 600], [98, 1, 60], [99, 1, 0], [100, 1, 60], [101, 1, 600], [102, 1, 60], [103, 1, 0], [104, 1, 60], [105, 1, 600], [106, 1, 60], [107, 1, 0], [108, 1, 60], [109, 1, 600], [110, 1, 60], [111, 1, 0], [122, 1, 0], [123, 1, 0]], "calls_event": [2085, 2086, 2087, 2088, 2089, 2090, 2091, 2092], "reroutes": ["Route=999"]}}, {"enemy_id": 11, "source": "local", "count": 1, "form_count": 1, "hp": 432000, "attack": 8960, "base_hp": 135000, "base_attack": 2800, "damage_type": "physical", "armor_defense": 800, "magic_defense": 50, "attack_speed": 1, "attack_wait": 70, "attack_interval": 212, "move_speed": 300.0, "gain_cost": 3, "dot_rate": 1.5, "assassin_resist": 1, "transform_resist": 100, "pattern_id": 2125808, "race_id": 6, "special_effect_id": 618, "master_id": 21804, "global_id": 2087, "commands": {"raw": "DoEnemy_RegistCommand(\"OnDestroy\", \"SetStageFlag(2, 1, 127);\");", "sets_flags": [[2, 1]], "on_destroy": true}}, {"enemy_id": 12, "source": "local", "count": 1, "form_count": 4, "tags": ["置物", "ステルスII", "ブロック不可"], "fixture": true, "hp": 480000, "base_hp": 150000, "damage_type": "physical", "armor_defense": 2000, "magic_defense": 60, "attack_speed": 1, "attack_wait": 60, "attack_interval": 167, "move_speed": 300.0, "gain_cost": 3, "dot_rate": 1.5, "pattern_id": 2097600, "change_to": 12, "master_id": 38054, "global_id": 11671, "to_global_id": 11663, "to_flag": [3, 1], "sp_change_to": [38055], "route_behaviour": {"transforms": [{"flag": 3, "val": 1, "to": 38056}, {"flag": 122, "val": 1}, {"flag": 126, "val": 1, "to": 38047}, {"flag": 123, "val": 1}, {}, {"to": 38056}, {"to": 38047}]}}, {"enemy_id": 12, "source": "local", "count": 1, "form_index": 1, "form_count": 4, "tags": ["置物", "ステルスII", "ブロック不可"], "fixture": true, "hp": 480000, "base_hp": 150000, "damage_type": "physical", "armor_defense": 2000, "magic_defense": 60, "attack_speed": 1, "attack_wait": 60, "attack_interval": 167, "move_speed": 300.0, "gain_cost": 3, "dot_rate": 1.5, "pattern_id": 2097600, "special_effect_id": 1899, "change_to": 15, "master_id": 38046, "global_id": 11663, "to_global_id": 11664, "from_flag": [3, 1], "to_flag": [122, 1]}, {"enemy_id": 12, "source": "local", "count": 1, "form_index": 2, "form_count": 4, "tags": ["置物", "ステルスII", "ブロック不可"], "fixture": true, "hp": 480000, "base_hp": 150000, "damage_type": "physical", "armor_defense": 2000, "magic_defense": 60, "attack_speed": 1, "attack_wait": 60, "attack_interval": 167, "move_speed": 300.0, "gain_cost": 3, "dot_rate": 1.5, "pattern_id": 2097600, "special_effect_id": 1900, "change_to": 12, "master_id": 38047, "global_id": 11664, "from_flag": [122, 1]}, {"enemy_id": 12, "source": "local", "count": 1, "form_index": 3, "form_count": 4, "tags": ["置物", "ステルスII", "ブロック不可"], "fixture": true, "hp": 480000, "base_hp": 150000, "damage_type": "physical", "armor_defense": 2000, "magic_defense": 60, "attack_speed": 1, "attack_wait": 60, "attack_interval": 167, "move_speed": 300.0, "gain_cost": 3, "dot_rate": 1.5, "pattern_id": 2097600, "special_effect_id": 1901, "change_to": 13, "master_id": 38055, "global_id": 11672, "from_condition": "sp_change"}, {"enemy_id": 17, "source": "local", "count": 1, "form_count": 2, "tags": ["置物", "ブロック不可"], "fixture": true, "hp": 480000, "base_hp": 150000, "damage_type": "physical", "armor_defense": 2000, "magic_defense": 60, "attack_speed": 1, "attack_wait": 60, "attack_interval": 182, "move_speed": 300.0, "gain_cost": 3, "dot_rate": 1.5, "pattern_id": 2157024, "change_to": 17, "master_id": 38029, "global_id": 11646, "to_global_id": 11645, "commands": {"raw": "DoEnemy_Performance(\"ENBSTL_NoAttack\"); DoEnemy_RegistCommand(\"OnDestroy\", \"SetStageFlag( 126 , 1 );\");", "sets_flags": [[126, 1]], "on_destroy": true}, "route_behaviour": {"transforms": [{}], "reroutes": ["Route=933"]}}, {"enemy_id": 17, "source": "local", "count": 1, "form_index": 1, "form_count": 2, "tags": ["置物", "ブロック不可"], "fixture": true, "hp": 480000, "base_hp": 150000, "damage_type": "physical", "armor_defense": 2000, "magic_defense": 60, "attack_speed": 1, "attack_wait": 60, "attack_interval": 182, "move_speed": 300.0, "gain_cost": 3, "dot_rate": 1.5, "pattern_id": 2157024, "special_effect_id": 1892, "change_to": 16, "master_id": 38028, "global_id": 11645}, {"enemy_id": 19, "source": "local", "count": 1, "form_count": 1, "tags": ["置物", "ブロック不可"], "fixture": true, "hp": 576000, "base_hp": 180000, "damage_type": "physical", "armor_defense": 1800, "magic_defense": 60, "attack_speed": 1, "attack_wait": 60, "attack_interval": 182, "move_speed": 450.0, "gain_cost": 3, "dot_rate": 1.5, "pattern_id": 2156976, "special_effect_id": 1905, "master_id": 22364, "global_id": 2647, "commands": {"raw": "DoEnemy_Performance(\"ENBSTL_NoAttack\");"}, "route_behaviour": {"reroutes": ["Route=5"]}}, {"enemy_id": 20, "source": "local", "count": 1, "form_count": 2, "hp": 492800, "attack": 3000, "base_hp": 154000, "base_attack": 3000, "damage_type": "magical", "armor_defense": 800, "magic_defense": 50, "attack_range": 300, "attack_speed": 1, "attack_wait": 60, "attack_interval": 185, "move_speed": 300.0, "gain_cost": 3, "dot_rate": 1.5, "assassin_resist": 1, "transform_resist": 1, "pattern_id": 2157104, "race_id": 6, "special_effect_id": 232, "change_to": 20, "change_condition": 2, "missile_id": 85, "missile": {"slow": [99, 0]}, "master_id": 22373, "global_id": 2656, "ranged": true, "to_condition": 2, "to_global_id": 2657, "commands": {"raw": "DoEnemy_RegistCommand(\"OnDestroy\", \"SetStageFlag(3, 1, 127);\");", "sets_flags": [[3, 1]], "on_destroy": true}}, {"enemy_id": 20, "source": "local", "count": 1, "form_index": 1, "form_count": 2, "hp": 588800, "attack": 5000, "base_hp": 184000, "base_attack": 5000, "damage_type": "magical", "armor_defense": 800, "magic_defense": 50, "attack_range": 260, "attack_speed": 1, "attack_wait": 90, "attack_interval": 247, "move_speed": 350.0, "gain_cost": 3, "dot_rate": 1.5, "assassin_resist": 1, "transform_resist": 100, "pattern_id": 2157120, "race_id": 6, "special_effect_id": 232, "missile_id": 1183, "missile": {"splash": 133}, "master_id": 22374, "global_id": 2657, "ranged": true, "from_condition": 2}, {"enemy_id": 22, "source": "local", "count": 1, "form_count": 2, "tags": ["アーマー"], "hp": 400000, "attack": 1500, "base_hp": 125000, "base_attack": 1500, "damage_type": "magical", "armor_defense": 800, "magic_defense": 30, "attack_range": 60, "attack_speed": 10, "attack_wait": 65, "attack_interval": 167, "move_speed": 600.0, "gain_cost": 3, "dot_rate": 1.5, "pattern_id": 2156800, "race_id": 16, "special_effect_id": 1879, "change_to": 22, "change_condition": 3, "missile_id": 45, "master_id": 38006, "global_id": 11623, "ranged": true, "to_condition": 3, "to_global_id": 11624, "spawn_sec": 1}, {"enemy_id": 22, "source": "local", "count": 1, "form_index": 1, "form_count": 2, "tags": ["アーマー"], "hp": 400000, "attack": 1800, "base_hp": 125000, "base_attack": 1800, "damage_type": "magical", "armor_defense": 800, "magic_defense": 30, "attack_range": 60, "attack_speed": 10, "attack_wait": 75, "attack_interval": 191, "move_speed": 600.0, "gain_cost": 3, "dot_rate": 1.5, "transform_resist": 100, "pattern_id": 2156816, "race_id": 16, "special_effect_id": 1879, "missile_id": 1165, "missile": {"splash": 133}, "master_id": 38007, "global_id": 11624, "ranged": true, "from_condition": 3}, {"enemy_id": 24, "source": "local", "count": 1, "form_count": 1, "hp": 441600, "attack": 3000, "base_hp": 138000, "base_attack": 3000, "damage_type": "physical", "armor_defense": 1000, "magic_defense": 20, "attack_range": 240, "attack_speed": 1, "attack_wait": 75, "attack_interval": 203, "move_speed": 1200.0, "gain_cost": 2, "dot_rate": 1.5, "transform_resist": 1, "pattern_id": 2156672, "race_id": 22, "special_effect_id": 1843, "missile_id": 1162, "missile": {"speed": 10.0, "splash": 140}, "master_id": 37999, "global_id": 11616, "ranged": true, "spawn_sec": 1}, {"enemy_id": 25, "source": "local", "count": 1, "form_count": 2, "hp": 345600, "attack": 2800, "base_hp": 108000, "base_attack": 2800, "damage_type": "physical", "armor_defense": 300, "magic_defense": 30, "attack_range": 270, "attack_speed": 1, "attack_wait": 40, "attack_interval": 127, "move_speed": 1600.0, "gain_cost": 3, "dot_rate": 1.5, "pattern_id": 2152064, "race_id": 19, "special_effect_id": 1695, "change_to": 25, "change_condition": 3, "missile_id": 560, "missile": {"speed": 6.0}, "master_id": 37353, "global_id": 10970, "ranged": true, "to_condition": 3, "to_global_id": 10971, "spawn_sec": 1}, {"enemy_id": 25, "source": "local", "count": 1, "form_index": 1, "form_count": 2, "tags": ["ステルス"], "hp": 345600, "attack": 1800, "base_hp": 108000, "base_attack": 1800, "damage_type": "physical", "armor_defense": 300, "magic_defense": 30, "attack_range": 270, "attack_speed": 1, "attack_wait": 10, "attack_interval": 47, "move_speed": 1600.0, "gain_cost": 3, "dot_rate": 1.5, "pattern_id": 2152080, "race_id": 19, "special_effect_id": 1696, "change_to": 26, "change_condition": 1, "missile_id": 101, "missile": {"speed": 2.0}, "master_id": 37354, "global_id": 10971, "ranged": true, "from_condition": 3, "variants": [{"hp": 345600, "attack": 1800, "base_hp": 108000, "base_attack": 1800, "damage_type": "physical", "armor_defense": 300, "magic_defense": 30, "attack_range": 270, "attack_speed": 1, "attack_wait": 10, "attack_interval": 47, "move_speed": 1600.0, "gain_cost": 3, "dot_rate": 1.5, "pattern_id": 2152096, "race_id": 19, "special_effect_id": 1696, "missile_id": 101, "missile": {"speed": 2.0}, "master_id": 37355, "global_id": 10972, "ranged": true}]}, {"enemy_id": 28, "source": "local", "count": 1, "form_count": 5, "hp": 300800, "attack": 3, "base_hp": 94000, "base_attack": 1, "damage_type": "physical", "armor_defense": 150, "magic_defense": 30, "attack_speed": 90, "attack_wait": 45, "attack_interval": 261, "move_speed": 600.0, "gain_cost": 3, "dot_rate": 1.5, "assassin_resist": 1, "transform_resist": 1, "pattern_id": 2157040, "race_id": 16, "special_effect_id": 1893, "change_to": 28, "master_id": 22377, "global_id": 2660, "to_global_id": 2661, "commands": {"raw": "FlagCheckCommandOrder(112, 1, 127, 1, \"DoEnemy_ModeChange();\"); FlagCheckCommandOrder(113, 1, 127, 1, \"DoEnemy_ModeChange();\"); FlagCheckCommandOrder(114, 1, 127, 1, \"DoEnemy_ModeChange();\"); FlagCheckCommandOrder(115, 1, 127, 1, \"DoEnemy_ModeChange();\"); FlagCheckCommandOrder(116, 1, 127, 1, \"DoEnemy_ModeChange();\"); DoEnemy_RegistCommand(\"OnDestroy\", \"SetStageFlag( 124 , 1 , 100 );\");", "sets_flags": [[124, 1]], "mode_changes": 5, "flag_checks": ["112, 1, 127, 1, \"DoEnemy_ModeChange(", "113, 1, 127, 1, \"DoEnemy_ModeChange(", "114, 1, 127, 1, \"DoEnemy_ModeChange(", "115, 1, 127, 1, \"DoEnemy_ModeChange(", "116, 1, 127, 1, \"DoEnemy_ModeChange("], "on_destroy": true}, "spawn_sec": 1}, {"enemy_id": 28, "source": "local", "count": 1, "form_index": 1, "form_count": 5, "hp": 300800, "attack": 3, "base_hp": 94000, "base_attack": 1, "damage_type": "physical", "armor_defense": 150, "magic_defense": 25, "attack_speed": 90, "attack_wait": 45, "attack_interval": 261, "move_speed": 600.0, "gain_cost": 3, "dot_rate": 1.5, "assassin_resist": 1, "transform_resist": 1, "pattern_id": 2157040, "race_id": 16, "special_effect_id": 1894, "change_to": 29, "master_id": 22378, "global_id": 2661, "to_global_id": 2662}, {"enemy_id": 28, "source": "local", "count": 1, "form_index": 2, "form_count": 5, "hp": 300800, "attack": 3, "base_hp": 94000, "base_attack": 1, "damage_type": "physical", "armor_defense": 150, "magic_defense": 25, "attack_speed": 90, "attack_wait": 45, "attack_interval": 261, "move_speed": 600.0, "gain_cost": 3, "dot_rate": 1.5, "assassin_resist": 1, "transform_resist": 1, "pattern_id": 2157040, "race_id": 16, "special_effect_id": 1895, "change_to": 30, "master_id": 22379, "global_id": 2662, "to_global_id": 2663}, {"enemy_id": 28, "source": "local", "count": 1, "form_index": 3, "form_count": 5, "hp": 300800, "attack": 3, "base_hp": 94000, "base_attack": 1, "damage_type": "physical", "armor_defense": 150, "magic_defense": 25, "attack_speed": 90, "attack_wait": 45, "attack_interval": 261, "move_speed": 600.0, "gain_cost": 3, "dot_rate": 1.5, "assassin_resist": 1, "transform_resist": 1, "pattern_id": 2157040, "race_id": 16, "special_effect_id": 1896, "change_to": 31, "master_id": 22380, "global_id": 2663, "to_global_id": 2664}, {"enemy_id": 28, "source": "local", "count": 1, "form_index": 4, "form_count": 5, "hp": 300800, "attack": 3, "base_hp": 94000, "base_attack": 1, "damage_type": "physical", "armor_defense": 150, "magic_defense": 25, "attack_speed": 90, "attack_wait": 45, "attack_interval": 261, "move_speed": 600.0, "gain_cost": 3, "dot_rate": 1.5, "assassin_resist": 1, "transform_resist": 100, "pattern_id": 2157040, "race_id": 16, "special_effect_id": 1897, "master_id": 22381, "global_id": 2664}, {"enemy_id": 33, "source": "local", "count": 28, "form_count": 1, "tags": ["アーマー", "ガレア近衛兵"], "hp": 32000, "attack": 800, "base_hp": 10000, "base_attack": 800, "damage_type": "physical", "armor_defense": 350, "magic_defense": 10, "attack_range": 140, "attack_speed": 1, "attack_wait": 45, "attack_interval": 143, "move_speed": 600.0, "gain_cost": 2, "dot_rate": 1.5, "assassin_resist": 1000, "transform_resist": 1000, "pattern_id": 2156832, "race_id": 20, "missile_id": 22, "missile": {"speed": 10.0}, "master_id": 38008, "global_id": 11625, "ranged": true, "spawn_sec": 258}, {"enemy_id": 34, "source": "local", "count": 4, "form_count": 2, "hp": 28800, "attack": 1500, "base_hp": 9000, "base_attack": 1500, "damage_type": "physical", "armor_defense": 1000, "magic_defense": 30, "attack_range": 100, "attack_speed": 60, "attack_wait": 60, "attack_interval": 214, "move_speed": 800.0, "gain_cost": 1, "dot_rate": 1.2000000476837158, "assassin_resist": 1000, "transform_resist": 1000, "pattern_id": 2154832, "race_id": 7, "special_effect_id": 1791, "change_to": 34, "change_condition": 4, "missile_id": 1124, "missile": {"speed": 5.0}, "master_id": 22119, "global_id": 2402, "ranged": true, "to_condition": 4, "to_ticks": 1, "to_global_id": 2403, "spawn_sec": 305}, {"enemy_id": 34, "source": "local", "count": 1, "form_index": 1, "form_count": 2, "hp": 28800, "attack": 3040, "base_hp": 9000, "base_attack": 950, "damage_type": "physical", "armor_defense": 1000, "magic_defense": 30, "attack_speed": 60, "attack_wait": 20, "attack_interval": 161, "move_speed": 800.0, "gain_cost": 1, "dot_rate": 1.2000000476837158, "assassin_resist": 1000, "transform_resist": 1000, "pattern_id": 2154848, "race_id": 7, "master_id": 22120, "global_id": 2403, "from_condition": 4, "trigger_ticks": 1}, {"enemy_id": 35, "source": "local", "count": 4, "form_count": 1, "hp": 28800, "attack": 3040, "base_hp": 9000, "base_attack": 950, "damage_type": "physical", "armor_defense": 1000, "magic_defense": 30, "attack_speed": 60, "attack_wait": 20, "attack_interval": 161, "move_speed": 800.0, "gain_cost": 1, "dot_rate": 1.2000000476837158, "assassin_resist": 1000, "transform_resist": 1000, "pattern_id": 2154848, "race_id": 7, "master_id": 22120, "global_id": 2403, "spawn_sec": 307}, {"enemy_id": 36, "source": "local", "count": 6, "form_count": 2, "hp": 32000, "attack": 2400, "base_hp": 10000, "base_attack": 750, "damage_type": "physical", "armor_defense": 500, "magic_defense": 20, "attack_speed": 90, "attack_wait": 10, "attack_interval": 171, "move_speed": 450.0, "gain_cost": 1, "dot_rate": 1.2999999523162842, "assassin_resist": 1500, "transform_resist": 1500, "pattern_id": 2101936, "race_id": 7, "change_to": 36, "master_id": 829, "global_id": 828, "to_global_id": 829, "spawn_sec": 312}, {"enemy_id": 36, "source": "local", "count": 1, "form_index": 1, "form_count": 2, "tags": ["狙う", "ブロック不可", "水面"], "hp": 32000, "base_hp": 10000, "damage_type": "physical", "armor_defense": 500, "magic_defense": 20, "attack_wait": 10, "move_speed": 500.0, "gain_cost": 1, "dot_rate": 1.2999999523162842, "assassin_resist": 1500, "transform_resist": 1500, "pattern_id": 2104960, "race_id": 7, "change_to": 35, "master_id": 830, "global_id": 829}, {"enemy_id": 38, "source": "local", "count": 9, "form_count": 1, "hp": 4160, "attack": 900, "base_hp": 1300, "base_attack": 900, "damage_type": "physical", "armor_defense": 100, "attack_range": 40, "attack_speed": 60, "attack_wait": 15, "attack_interval": 71, "move_speed": 1700.0, "gain_cost": 1, "dot_rate": 1.5, "assassin_resist": 1000, "transform_resist": 1000, "pattern_id": 2111744, "race_id": 13, "special_effect_id": 191, "missile_id": 45, "master_id": 35777, "global_id": 9394, "ranged": true, "spawn_sec": 325}, {"enemy_id": 39, "source": "local", "count": 8, "form_count": 1, "tags": ["鳥", "水棲"], "hp": 28800, "base_hp": 9000, "damage_type": "physical", "armor_defense": 600, "attack_speed": 1, "move_speed": 1400.0, "gain_cost": 2, "dot_rate": 1.399999976158142, "assassin_resist": 1000, "transform_resist": 1000, "pattern_id": 2132432, "race_id": 11, "master_id": 34505, "global_id": 8122, "spawn_sec": 331}, {"enemy_id": 40, "source": "local", "count": 4, "form_count": 1, "hp": 48000, "attack": 1300, "base_hp": 15000, "base_attack": 1300, "damage_type": "magical", "armor_defense": 600, "magic_defense": 35, "attack_range": 220, "attack_speed": 60, "attack_wait": 100, "attack_interval": 261, "move_speed": 300.0, "gain_cost": 3, "dot_rate": 1.2999999523162842, "assassin_resist": 1, "transform_resist": 100, "pattern_id": 2106592, "race_id": 7, "missile_id": 85, "missile": {"slow": [99, 0]}, "master_id": 835, "global_id": 834, "ranged": true, "spawn_sec": 341}, {"enemy_id": 41, "source": "local", "count": 4, "form_count": 1, "hp": 28800, "attack": 1280, "base_hp": 9000, "base_attack": 400, "damage_type": "physical", "armor_defense": 150, "magic_defense": 30, "attack_speed": 1, "attack_wait": 5, "attack_interval": 60, "move_speed": 2400.0, "gain_cost": 1, "dot_rate": 1.399999976158142, "assassin_resist": 1500, "transform_resist": 1500, "pattern_id": 2123616, "race_id": 7, "master_id": 32742, "global_id": 6360, "spawn_sec": 341}, {"enemy_id": 42, "source": "local", "count": 15, "form_count": 2, "hp": 38400, "attack": 400, "base_hp": 12000, "base_attack": 400, "damage_type": "magical", "armor_defense": 700, "magic_defense": 40, "attack_range": 25, "attack_speed": 1, "attack_interval": 217, "move_speed": 600.0, "gain_cost": 3, "dot_rate": 1.5, "pattern_id": 2148400, "race_id": 6, "special_effect_id": 1556, "change_to": 42, "change_condition": 2, "missile_id": 640, "master_id": 21798, "global_id": 2081, "ranged": true, "to_condition": 2, "to_global_id": 2086, "route_behaviour": {"reroutes": ["Route=14", "Route=15", "Route=2", "Route=935"]}, "spawn_sec": 354}, {"enemy_id": 42, "source": "local", "count": 1, "form_index": 1, "form_count": 2, "hp": 3, "attack": 400, "base_hp": 1, "base_attack": 400, "damage_type": "magical", "armor_defense": 700, "magic_defense": 40, "attack_range": 80, "attack_speed": 1, "attack_interval": 217, "move_speed": 600.0, "gain_cost": 3, "dot_rate": 1.5, "pattern_id": 2148672, "race_id": 6, "special_effect_id": 1564, "missile_id": 640, "master_id": 21803, "global_id": 2086, "ranged": true, "from_condition": 2}, {"enemy_id": 44, "source": "local", "count": 8, "form_count": 1, "tags": ["鳥"], "hp": 192000, "attack": 700, "base_hp": 60000, "base_attack": 700, "damage_type": "physical", "armor_defense": 450, "magic_defense": 40, "attack_range": 350, "attack_speed": 1, "attack_wait": 30, "attack_interval": 131, "move_speed": 300.0, "gain_cost": 3, "dot_rate": 1.5, "assassin_resist": 1, "transform_resist": 1, "pattern_id": 2125824, "race_id": 11, "special_effect_id": 619, "missile_id": 207, "missile": {"speed": 2.0}, "master_id": 32932, "global_id": 6549, "ranged": true, "spawn_sec": 364}, {"enemy_id": 45, "source": "local", "count": 4, "form_count": 1, "tags": ["精霊(雷)"], "hp": 9600, "attack": 100, "base_hp": 3000, "base_attack": 100, "damage_type": "magical", "armor_defense": 10, "attack_range": 80, "attack_speed": 25, "attack_wait": 15, "attack_interval": 40, "move_speed": 1200.0, "gain_cost": 3, "dot_rate": 1.0, "assassin_resist": 100, "transform_resist": 100, "pattern_id": 2117408, "special_effect_id": 350, "missile_id": 85, "missile": {"slow": [99, 0]}, "master_id": 31520, "global_id": 5139, "ranged": true, "spawn_sec": 435}, {"enemy_id": 46, "source": "local", "count": 4, "form_count": 1, "tags": ["精霊(雷)"], "hp": 19200, "attack": 200, "base_hp": 6000, "base_attack": 200, "damage_type": "magical", "armor_defense": 20, "attack_range": 80, "attack_speed": 25, "attack_wait": 15, "attack_interval": 40, "move_speed": 1200.0, "gain_cost": 3, "dot_rate": 1.2999999523162842, "assassin_resist": 100, "transform_resist": 100, "pattern_id": 2117408, "special_effect_id": 351, "missile_id": 85, "missile": {"slow": [99, 0]}, "master_id": 31521, "global_id": 5140, "ranged": true, "spawn_sec": 440}, {"enemy_id": 47, "source": "local", "count": 8, "form_count": 1, "tags": ["精霊(雷)"], "hp": 44800, "attack": 350, "base_hp": 14000, "base_attack": 350, "damage_type": "magical", "armor_defense": 30, "attack_range": 80, "attack_speed": 25, "attack_wait": 15, "attack_interval": 40, "move_speed": 1200.0, "gain_cost": 3, "dot_rate": 1.600000023841858, "assassin_resist": 100, "transform_resist": 100, "pattern_id": 2117408, "special_effect_id": 352, "missile_id": 85, "missile": {"slow": [99, 0]}, "master_id": 31522, "global_id": 5141, "ranged": true, "spawn_sec": 445}, {"enemy_id": 48, "source": "local", "count": 3, "form_count": 2, "tags": ["置物", "ステルスII", "ブロック不可"], "fixture": true, "hp": 31999997, "attack": 16000, "base_hp": 9999999, "base_attack": 5000, "damage_type": "magical", "attack_speed": 1, "attack_wait": 300, "move_speed": 500.0, "gain_cost": 3, "dot_rate": 1.5, "pattern_id": 2137216, "special_effect_id": 516, "change_to": 48, "master_id": 22375, "global_id": 2658, "to_global_id": 2659, "to_flag": [6, 1], "sp_change_to": [22376], "route_behaviour": {"transforms": [{"flag": 6, "val": 1}, {"flag": 7, "val": 1}, {"flag": 10, "val": 1}, {"flag": 11, "val": 1}, {"flag": 14, "val": 1}, {"flag": 15, "val": 1}, {"flag": 18, "val": 1}, {"flag": 19, "val": 1}, {"flag": 22, "val": 1}, {"flag": 23, "val": 1}, {"flag": 26, "val": 1}, {"flag": 27, "val": 1}, {"flag": 30, "val": 1}, {"flag": 31, "val": 1}, {"flag": 34, "val": 1}, {"flag": 35, "val": 1}, {"flag": 38, "val": 1}, {"flag": 39, "val": 1}, {"flag": 42, "val": 1}, {"flag": 43, "val": 1}, {"flag": 46, "val": 1}, {"flag": 47, "val": 1}, {"flag": 50, "val": 1}, {"flag": 51, "val": 1}, {"flag": 54, "val": 1}, {"flag": 55, "val": 1}, {"flag": 58, "val": 1}, {"flag": 59, "val": 1}, {"flag": 62, "val": 1}, {"flag": 63, "val": 1}, {"flag": 66, "val": 1}, {"flag": 67, "val": 1}, {"flag": 70, "val": 1}, {"flag": 71, "val": 1}, {"flag": 74, "val": 1}, {"flag": 75, "val": 1}, {"flag": 78, "val": 1}, {"flag": 79, "val": 1}, {"flag": 82, "val": 1}, {"flag": 83, "val": 1}, {"flag": 86, "val": 1}, {"flag": 87, "val": 1}, {"flag": 90, "val": 1}, {"flag": 91, "val": 1}, {"flag": 94, "val": 1}, {"flag": 95, "val": 1}, {"flag": 98, "val": 1}, {"flag": 99, "val": 1}, {"flag": 102, "val": 1}, {"flag": 103, "val": 1}, {"flag": 106, "val": 1}, {"flag": 107, "val": 1}, {"flag": 110, "val": 1}, {"flag": 111, "val": 1}]}, "spawn_sec": 454}, {"enemy_id": 48, "source": "local", "count": 1, "form_index": 1, "form_count": 2, "tags": ["置物", "ステルスII", "ブロック不可"], "fixture": true, "hp": 31999997, "attack": 5000, "base_hp": 9999999, "base_attack": 5000, "damage_type": "true", "attack_range": 100, "attack_speed": 1, "attack_wait": 300, "move_speed": 500.0, "gain_cost": 3, "dot_rate": 1.5, "pattern_id": 2137216, "special_effect_id": 1904, "change_to": 47, "missile_id": 1185, "missile": {"speed": 10.0}, "master_id": 22376, "global_id": 2659, "ranged": true, "from_flag": [6, 1]}, {"enemy_id": 50, "source": "local", "count": 1, "form_count": 4, "tags": ["ディアス"], "hp": 1808000, "attack": 18000, "base_hp": 565000, "base_attack": 18000, "damage_type": "physical", "armor_defense": 3000, "magic_defense": 80, "attack_range": 400, "attack_speed": 1, "attack_wait": 60, "attack_interval": 221, "move_speed": 300.0, "gain_cost": 3, "dot_rate": 1.2999999523162842, "pattern_id": 2156912, "race_id": 19, "special_effect_id": 1884, "change_to": 50, "missile_id": 1180, "missile": {"speed": 15.0, "splash": 107}, "master_id": 22367, "global_id": 2650, "ranged": true, "to_global_id": 2651, "to_flag": [4, 1], "commands": {"raw": "DoEnemy_Performance(\"ENBSTL_StandMotion\");"}, "route_behaviour": {"transforms": [{"flag": 4, "val": 1}, {"flag": 5, "val": 1}, {"flag": 6, "val": 1}, {"flag": 7, "val": 1}, {"flag": 8, "val": 1}, {"flag": 9, "val": 1}, {"flag": 10, "val": 1}, {"flag": 11, "val": 1}, {"flag": 12, "val": 1}, {"flag": 13, "val": 1}, {"flag": 14, "val": 1}, {"flag": 15, "val": 1}, {"flag": 16, "val": 1}, {"flag": 17, "val": 1}, {"flag": 18, "val": 1}, {"flag": 19, "val": 1}, {"flag": 20, "val": 1}, {"flag": 21, "val": 1}, {"flag": 22, "val": 1}, {"flag": 23, "val": 1}, {"flag": 24, "val": 1}, {"flag": 25, "val": 1}, {"flag": 26, "val": 1}, {"flag": 27, "val": 1}, {"flag": 28, "val": 1}, {"flag": 29, "val": 1}, {"flag": 30, "val": 1}, {"flag": 31, "val": 1}, {"flag": 32, "val": 1}, {"flag": 33, "val": 1}, {"flag": 34, "val": 1}, {"flag": 35, "val": 1}, {"flag": 36, "val": 1}, {"flag": 37, "val": 1}, {"flag": 38, "val": 1}, {"flag": 39, "val": 1}, {"flag": 40, "val": 1}, {"flag": 41, "val": 1}, {"flag": 42, "val": 1}, {"flag": 43, "val": 1}, {"flag": 44, "val": 1}, {"flag": 45, "val": 1}, {"flag": 46, "val": 1}, {"flag": 47, "val": 1}, {"flag": 48, "val": 1}, {"flag": 49, "val": 1}, {"flag": 50, "val": 1}, {"flag": 51, "val": 1}, {"flag": 52, "val": 1}, {"flag": 53, "val": 1}, {"flag": 54, "val": 1}, {"flag": 55, "val": 1}, {"flag": 56, "val": 1}, {"flag": 57, "val": 1}, {"flag": 58, "val": 1}, {"flag": 59, "val": 1}, {"flag": 60, "val": 1}, {"flag": 61, "val": 1}, {"flag": 62, "val": 1}, {"flag": 63, "val": 1}, {"flag": 64, "val": 1}, {"flag": 65, "val": 1}, {"flag": 66, "val": 1}, {"flag": 67, "val": 1}, {"flag": 68, "val": 1}, {"flag": 69, "val": 1}, {"flag": 70, "val": 1}, {"flag": 71, "val": 1}, {"flag": 72, "val": 1}, {"flag": 73, "val": 1}, {"flag": 74, "val": 1}, {"flag": 75, "val": 1}, {"flag": 76, "val": 1}, {"flag": 77, "val": 1}, {"flag": 78, "val": 1}, {"flag": 79, "val": 1}, {"flag": 80, "val": 1}, {"flag": 81, "val": 1}, {"flag": 82, "val": 1}, {"flag": 83, "val": 1}, {"flag": 84, "val": 1}, {"flag": 85, "val": 1}, {"flag": 86, "val": 1}, {"flag": 87, "val": 1}, {"flag": 88, "val": 1}, {"flag": 89, "val": 1}, {"flag": 90, "val": 1}, {"flag": 91, "val": 1}, {"flag": 92, "val": 1}, {"flag": 93, "val": 1}, {"flag": 94, "val": 1}, {"flag": 95, "val": 1}, {"flag": 96, "val": 1}, {"flag": 97, "val": 1}, {"flag": 98, "val": 1}, {"flag": 99, "val": 1}, {"flag": 100, "val": 1}, {"flag": 101, "val": 1}, {"flag": 102, "val": 1}, {"flag": 103, "val": 1}, {"flag": 104, "val": 1}, {"flag": 105, "val": 1}, {"flag": 106, "val": 1}, {"flag": 107, "val": 1}, {"flag": 108, "val": 1}, {"flag": 109, "val": 1}, {"flag": 110, "val": 1}, {"flag": 111, "val": 1}], "sets_flags": [[0, 1, 0], [117, 1, 0], [125, 1, 0]]}, "spawn_sec": 454}, {"enemy_id": 50, "source": "local", "count": 1, "form_index": 1, "form_count": 4, "tags": ["ステルスII", "ブロック不可", "ディアス"], "hp": 1808000, "base_hp": 565000, "damage_type": "physical", "armor_defense": 3000, "magic_defense": 80, "attack_speed": 1, "attack_interval": 52, "move_speed": 1.0, "gain_cost": 3, "dot_rate": 1.2999999523162842, "pattern_id": 2156928, "race_id": 19, "change_to": 51, "master_id": 22368, "global_id": 2651, "to_global_id": 2652, "from_flag": [4, 1], "to_flag": [5, 1]}, {"enemy_id": 50, "source": "local", "count": 1, "form_index": 2, "form_count": 4, "tags": ["ディアス"], "hp": 1808000, "attack": 7000, "base_hp": 565000, "base_attack": 7000, "damage_type": "true", "armor_defense": 3000, "magic_defense": 80, "attack_range": 2000, "attack_speed": 1, "attack_wait": 10, "attack_interval": 71, "move_speed": 1.0, "gain_cost": 3, "dot_rate": 1.2999999523162842, "pattern_id": 2156944, "race_id": 19, "special_effect_id": 1885, "change_to": 52, "missile_id": 640, "master_id": 22369, "global_id": 2652, "ranged": true, "to_global_id": 2653, "from_flag": [5, 1], "to_flag": [6, 1]}, {"enemy_id": 50, "source": "local", "count": 1, "form_index": 3, "form_count": 4, "tags": ["ステルスII", "ブロック不可", "ディアス"], "hp": 1808000, "base_hp": 565000, "damage_type": "physical", "armor_defense": 3000, "magic_defense": 80, "attack_speed": 1, "attack_interval": 102, "move_speed": 1.0, "gain_cost": 3, "dot_rate": 1.2999999523162842, "pattern_id": 2156960, "race_id": 19, "change_to": 49, "master_id": 22370, "global_id": 2653, "from_flag": [6, 1]}, {"enemy_id": 54, "source": "local", "count": 4, "form_count": 2, "hp": 96000, "attack": 2000, "base_hp": 30000, "base_attack": 2000, "damage_type": "magical", "armor_defense": 4000, "magic_defense": 10, "attack_range": 140, "attack_speed": 1, "attack_wait": 120, "attack_interval": 361, "move_speed": 4000.0, "gain_cost": 3, "dot_rate": 1.7000000476837158, "assassin_resist": 1, "pattern_id": 2113008, "race_id": 6, "change_to": 54, "missile_id": 171, "missile": {"speed": 6.0, "splash": 267}, "master_id": 35821, "global_id": 9438, "ranged": true, "to_global_id": 7446, "route_behaviour": {"transforms": [{"wait": 1000}]}, "spawn_sec": 457}, {"enemy_id": 54, "source": "local", "count": 1, "form_index": 1, "form_count": 2, "hp": 96000, "attack": 2000, "base_hp": 30000, "base_attack": 2000, "damage_type": "magical", "armor_defense": 4000, "magic_defense": 10, "attack_range": 140, "attack_speed": 1, "attack_wait": 120, "attack_interval": 361, "move_speed": 250.0, "gain_cost": 3, "dot_rate": 1.7000000476837158, "assassin_resist": 1, "transform_resist": 100, "pattern_id": 2113008, "race_id": 6, "missile_id": 171, "missile": {"speed": 6.0, "splash": 267}, "master_id": 33829, "global_id": 7446, "ranged": true}, {"enemy_id": 56, "source": "local", "count": 14, "form_count": 1, "hp": 76800, "attack": 7680, "base_hp": 24000, "base_attack": 2400, "damage_type": "physical", "armor_defense": 4000, "magic_defense": 10, "attack_speed": 1, "attack_wait": 60, "attack_interval": 220, "move_speed": 2000.0, "gain_cost": 3, "dot_rate": 1.5, "assassin_resist": 1, "transform_resist": 100, "pattern_id": 2127024, "race_id": 6, "master_id": 33410, "global_id": 7027, "spawn_sec": 459}, {"enemy_id": 57, "source": "local", "count": 14, "form_count": 1, "hp": 32000, "attack": 3200, "base_hp": 10000, "base_attack": 1000, "damage_type": "physical", "armor_defense": 900, "attack_speed": 55, "attack_wait": 60, "attack_interval": 260, "move_speed": 500.0, "gain_cost": 3, "dot_rate": 1.5, "assassin_resist": 100, "transform_resist": 100, "pattern_id": 2107616, "race_id": 6, "change_to": 57, "master_id": 880, "global_id": 879, "route_behaviour": {"transforms": [{"wait": 150}]}, "spawn_sec": 468}, {"enemy_id": 59, "source": "local", "count": 8, "form_count": 1, "hp": 9600, "base_hp": 3000, "damage_type": "physical", "armor_defense": 1500, "magic_defense": 10, "attack_wait": 30, "move_speed": 500.0, "dot_rate": 1.2000000476837158, "assassin_resist": 100, "transform_resist": 100, "pattern_id": 2114176, "race_id": 6, "special_effect_id": 855, "master_id": 34030, "global_id": 7647, "spawn_sec": 479}, {"enemy_id": 60, "source": "local", "count": 22, "form_count": 1, "tags": ["アーマー"], "hp": 12800, "attack": 700, "base_hp": 4000, "base_attack": 700, "damage_type": "magical", "armor_defense": 500, "attack_range": 200, "attack_speed": 80, "attack_wait": 70, "attack_interval": 221, "move_speed": 500.0, "gain_cost": 3, "dot_rate": 1.5, "assassin_resist": 100, "transform_resist": 100, "pattern_id": 2109328, "race_id": 6, "special_effect_id": 232, "change_to": 60, "missile_id": 85, "missile": {"slow": [99, 0]}, "master_id": 35830, "global_id": 9447, "ranged": true, "route_behaviour": {"transforms": [{"wait": 150}]}, "spawn_sec": 487}, {"enemy_id": 62, "source": "local", "count": 11, "form_count": 1, "hp": 80000, "attack": 700, "base_hp": 25000, "base_attack": 700, "damage_type": "physical", "armor_defense": 300, "magic_defense": 25, "attack_range": 400, "attack_speed": 70, "attack_wait": 35, "attack_interval": 130, "move_speed": 300.0, "gain_cost": 3, "dot_rate": 1.5, "assassin_resist": 1, "transform_resist": 100, "pattern_id": 2105472, "race_id": 6, "special_effect_id": 73, "missile_id": 151, "missile": {"speed": 3.0}, "master_id": 652, "global_id": 651, "ranged": true, "spawn_sec": 502}, {"enemy_id": 63, "source": "local", "count": 10, "form_count": 1, "hp": 48000, "attack": 200, "base_hp": 15000, "base_attack": 200, "damage_type": "magical", "armor_defense": 200, "magic_defense": 60, "attack_range": 140, "attack_speed": 1, "attack_wait": 60, "attack_interval": 173, "move_speed": 600.0, "gain_cost": 1, "dot_rate": 1.5, "assassin_resist": 1000, "transform_resist": 1000, "pattern_id": 2156176, "race_id": 6, "special_effect_id": 43, "missile_id": 45, "master_id": 38051, "global_id": 11668, "ranged": true, "spawn_sec": 568}, {"enemy_id": 64, "source": "local", "count": 2, "form_count": 2, "hp": 96000, "attack": 8960, "base_hp": 30000, "base_attack": 2800, "damage_type": "physical", "armor_defense": 4000, "magic_defense": 10, "attack_speed": 120, "attack_wait": 10, "attack_interval": 251, "move_speed": 4000.0, "gain_cost": 3, "dot_rate": 1.899999976158142, "assassin_resist": 1, "transform_resist": 1, "pattern_id": 2107424, "race_id": 6, "change_to": 64, "master_id": 574, "global_id": 573, "to_global_id": 570, "route_behaviour": {"transforms": [{"wait": 1000}]}, "spawn_sec": 575}, {"enemy_id": 64, "source": "local", "count": 1, "form_index": 1, "form_count": 2, "hp": 96000, "attack": 8960, "base_hp": 30000, "base_attack": 2800, "damage_type": "physical", "armor_defense": 4000, "magic_defense": 10, "attack_speed": 120, "attack_wait": 10, "attack_interval": 251, "move_speed": 250.0, "gain_cost": 3, "dot_rate": 1.899999976158142, "assassin_resist": 1, "transform_resist": 100, "pattern_id": 2107408, "race_id": 6, "master_id": 571, "global_id": 570}], "popups": ["亜神ヘルメルクは、\n自身の攻撃力の値で\n自身を除く周囲の敵を回復します。\n\nまた亜神ヘルメルクは\n一定範囲内の味方ユニットの\n防御力、魔法耐性を半減させます。\n　　　　　　(1/2)", "HPが50％以下になると\n回復行動を止め、\n遠距離攻撃を行うようになり\nブロックされていない間は\n味方の遠距離攻撃の\n対象にならなくなります。\n\n　　　　　　(2/2)", "ヘラクレイアから攻撃を\n受けると「毒」状態になり、\n一定時間継続ダメージを受けます。\n\n毒によるダメージは、女神の加護や\n攻撃の無効化の影響を受けません。\n\n　　　　　　(1/2)", "ヘラクレイアの攻撃を受けた\n味方ユニットは2秒間、\n攻撃力が減少します。\n\nこの効果は、状態異常に対する\nユニットの能力では\n軽減、無効化できません。\n　　　　　　(2/2)", "ホルミースの影響により\n天使と天界兵は、\n攻撃と防御がアップします。\n\nこの効果はミッションの\n時間が経過するほど\n強力になります。", "ガレアがいる間は\n全ての敵ユニットの\n攻撃と防御がアップします。", "ガレアの近衛兵は\nガレアが生存していると\n攻撃と防御が\n大幅にアップします。"], "active": true}