{"quest_id": 8612, "name": "緻密な計画", "description": "もしも闇の組織の計画が成功して、\n王子たちが助力を得られなかったら……？\n＜見張りに見つかると敵の攻防大幅上昇＞\n神級EX（★１獲得の目安：平均覚醒Lv25）", "modifier_notes": ["見張りに見つかると敵の攻防大幅上昇"], "event": "真夏のカオスリゾート", "event_category": "History", "mission_id": 920235, "map_no": 9380, "level": 100, "multiplier": 1.0, "charisma": 75, "capacity": 8, "modifiers": [{"kind": "term", "influence": 11, "params": [200], "expression": "IsStageFlag( 1);", "expression_human": "stage flag 1 is set"}, {"kind": "term", "influence": 18, "params": [200], "expression": "IsStageFlag( 1);", "expression_human": "stage flag 1 is set"}], "enemies": [{"enemy_id": 1, "source": "local", "count": 2, "form_count": 2, "hp": 5000, "attack": 150, "base_hp": 5000, "base_attack": 150, "damage_type": "physical", "armor_defense": 100, "attack_range": 155, "attack_speed": 1, "attack_wait": 80, "attack_interval": 223, "move_speed": 800.0, "gain_cost": 2, "dot_rate": 1.5, "assassin_resist": 1000, "transform_resist": 1000, "pattern_id": 2112480, "race_id": 16, "special_effect_id": 205, "change_to": 1, "change_condition": 4, "missile_id": 26, "master_id": 30687, "global_id": 4306, "ranged": true, "to_condition": 4, "to_ticks": 1, "to_global_id": 4307, "route_behaviour": {"sets_flags": [[1, 0, 0], [1, 1, 0]]}, "spawn_sec": 1}, {"enemy_id": 1, "source": "local", "count": 1, "form_index": 1, "form_count": 2, "hp": 5000, "attack": 150, "base_hp": 5000, "base_attack": 150, "damage_type": "physical", "armor_defense": 100, "attack_range": 155, "attack_speed": 1, "attack_wait": 80, "attack_interval": 223, "move_speed": 800.0, "gain_cost": 2, "dot_rate": 1.5, "assassin_resist": 1000, "transform_resist": 1000, "pattern_id": 2112496, "race_id": 16, "missile_id": 26, "master_id": 30688, "global_id": 4307, "ranged": true, "from_condition": 4, "trigger_ticks": 1}, {"enemy_id": 3, "source": "local", "count": 1, "form_count": 1, "hp": 60000, "attack": 800, "base_hp": 60000, "base_attack": 800, "damage_type": "physical", "armor_defense": 600, "magic_defense": 20, "attack_range": 200, "attack_speed": 1, "attack_wait": 37, "attack_interval": 169, "move_speed": 750.0, "gain_cost": 3, "dot_rate": 1.5, "assassin_resist": 1, "transform_resist": 100, "pattern_id": 2126336, "race_id": 16, "special_effect_id": 525, "missile_id": 513, "missile": {"speed": 8.0, "splash": 87}, "master_id": 33016, "global_id": 6633, "ranged": true, "commands": {"raw": "DoEnemy_RegistCommand(\"OnDestroy\", \"SetStageFlag(0, 1);\");", "sets_flags": [[0, 1]], "on_destroy": true}, "spawn_sec": 5}, {"enemy_id": 4, "source": "local", "count": 52, "form_count": 3, "tags": ["機械"], "hp": 9500, "attack": 400, "base_hp": 9500, "base_attack": 400, "damage_type": "physical", "armor_defense": 170, "magic_defense": 10, "attack_range": 120, "attack_speed": 1, "attack_wait": 107, "attack_interval": 300, "move_speed": 750.0, "gain_cost": 1, "dot_rate": 1.100000023841858, "assassin_resist": 1, "transform_resist": 1, "pattern_id": 2126400, "special_effect_id": 658, "change_to": 4, "missile_id": 515, "missile": {"speed": 8.0, "splash": 67}, "master_id": 33022, "global_id": 6639, "ranged": true, "to_global_id": 6638, "route_behaviour": {"reroutes": ["Route=999"]}, "spawn_sec": 6}, {"enemy_id": 4, "source": "local", "count": 1, "form_index": 1, "form_count": 3, "tags": ["機械"], "hp": 9500, "attack": 400, "base_hp": 9500, "base_attack": 400, "damage_type": "physical", "armor_defense": 170, "magic_defense": 10, "attack_range": 120, "attack_speed": 1, "attack_wait": 107, "attack_interval": 300, "move_speed": 500.0, "gain_cost": 1, "dot_rate": 1.100000023841858, "assassin_resist": 1, "transform_resist": 1, "pattern_id": 2126416, "special_effect_id": 659, "change_to": 5, "missile_id": 515, "missile": {"speed": 8.0, "splash": 67}, "master_id": 33021, "global_id": 6638, "ranged": true, "to_global_id": 6637}, {"enemy_id": 4, "source": "local", "count": 1, "form_index": 2, "form_count": 3, "tags": ["機械"], "hp": 9500, "attack": 400, "base_hp": 9500, "base_attack": 400, "damage_type": "physical", "armor_defense": 170, "magic_defense": 10, "attack_range": 120, "attack_speed": 1, "attack_wait": 107, "attack_interval": 300, "move_speed": 750.0, "gain_cost": 1, "dot_rate": 1.100000023841858, "assassin_resist": 1, "transform_resist": 1, "pattern_id": 2126400, "special_effect_id": 657, "change_to": 4, "missile_id": 515, "missile": {"speed": 8.0, "splash": 67}, "master_id": 33020, "global_id": 6637, "ranged": true}, {"enemy_id": 7, "source": "local", "count": 1, "form_count": 1, "hp": 18000, "attack": 1600, "base_hp": 18000, "base_attack": 1600, "damage_type": "physical", "armor_defense": 500, "magic_defense": 20, "attack_range": 220, "attack_speed": 90, "attack_wait": 100, "attack_interval": 251, "move_speed": 1000.0, "gain_cost": 3, "dot_rate": 1.5, "assassin_resist": 1, "transform_resist": 100, "pattern_id": 2109120, "race_id": 16, "special_effect_id": 523, "missile_id": 26, "master_id": 32551, "global_id": 6170, "ranged": true, "spawn_sec": 28}, {"enemy_id": 8, "source": "local", "count": 1, "form_count": 2, "tags": ["機械"], "hp": 32000, "attack": 1050, "base_hp": 32000, "base_attack": 1050, "damage_type": "true", "armor_defense": 600, "attack_speed": 1, "attack_wait": 20, "attack_interval": 90, "move_speed": 2000.0, "gain_cost": 3, "dot_rate": 1.5, "assassin_resist": 1, "transform_resist": 1, "pattern_id": 2126672, "race_id": 16, "special_effect_id": 663, "change_to": 8, "change_condition": 2, "master_id": 33318, "global_id": 6935, "to_condition": 2, "to_global_id": 6936, "spawn_sec": 30}, {"enemy_id": 8, "source": "local", "count": 1, "form_index": 1, "form_count": 2, "tags": ["機械", "ステルス"], "hp": 90000, "attack": 1200, "base_hp": 90000, "base_attack": 1200, "damage_type": "true", "armor_defense": 600, "attack_speed": 1, "attack_wait": 20, "attack_interval": 58, "gain_cost": 3, "dot_rate": 1.5, "pattern_id": 2126688, "race_id": 16, "special_effect_id": 664, "master_id": 33319, "global_id": 6936, "from_condition": 2}, {"enemy_id": 10, "source": "local", "count": 8, "form_count": 1, "hp": 4500, "attack": 130, "base_hp": 4500, "base_attack": 130, "damage_type": "physical", "armor_defense": 150, "attack_speed": 16, "attack_wait": 10, "attack_interval": 53, "move_speed": 1100.0, "gain_cost": 1, "dot_rate": 1.5, "assassin_resist": 1000, "transform_resist": 1000, "pattern_id": 2103520, "race_id": 16, "master_id": 453, "global_id": 452, "spawn_sec": 32}, {"enemy_id": 11, "source": "local", "count": 10, "form_count": 1, "tags": ["ステルス"], "hp": 2000, "attack": 130, "base_hp": 2000, "base_attack": 130, "damage_type": "physical", "armor_defense": 100, "attack_speed": 16, "attack_wait": 10, "attack_interval": 53, "move_speed": 1300.0, "gain_cost": 1, "dot_rate": 1.5, "assassin_resist": 1000, "transform_resist": 1000, "pattern_id": 2136016, "race_id": 16, "master_id": 34785, "global_id": 8402, "spawn_sec": 53}, {"enemy_id": 12, "source": "local", "count": 32, "form_count": 1, "tags": ["ステルス"], "hp": 9000, "attack": 320, "base_hp": 9000, "base_attack": 320, "damage_type": "physical", "armor_defense": 150, "attack_speed": 16, "attack_wait": 10, "attack_interval": 53, "move_speed": 1100.0, "gain_cost": 2, "dot_rate": 1.5, "assassin_resist": 100, "transform_resist": 100, "pattern_id": 2136048, "race_id": 16, "special_effect_id": 54, "master_id": 34788, "global_id": 8405, "spawn_sec": 78}, {"enemy_id": 13, "source": "local", "count": 2, "form_count": 2, "tags": ["ステルス"], "hp": 6000, "attack": 500, "base_hp": 6000, "base_attack": 500, "damage_type": "physical", "armor_defense": 300, "magic_defense": 10, "attack_speed": 5, "attack_wait": 25, "attack_interval": 106, "move_speed": 1000.0, "gain_cost": 1, "dot_rate": 1.5, "assassin_resist": 100, "transform_resist": 100, "pattern_id": 2136032, "race_id": 16, "special_effect_id": 61, "change_to": 13, "master_id": 34786, "global_id": 8403, "to_global_id": 8404, "route_behaviour": {"transforms": [{"wait": 2000}]}, "spawn_sec": 90}, {"enemy_id": 13, "source": "local", "count": 1, "form_index": 1, "form_count": 2, "hp": 6000, "attack": 750, "base_hp": 6000, "base_attack": 750, "damage_type": "physical", "armor_defense": 300, "magic_defense": 10, "attack_range": 300, "attack_speed": 90, "attack_wait": 120, "attack_interval": 331, "move_speed": 1000.0, "gain_cost": 1, "dot_rate": 1.5, "assassin_resist": 100, "transform_resist": 100, "pattern_id": 2136064, "race_id": 16, "special_effect_id": 61, "change_to": 12, "missile_id": 26, "master_id": 34787, "global_id": 8404, "ranged": true}, {"enemy_id": 15, "source": "local", "count": 1, "form_count": 1, "hp": 9500, "attack": 3500, "base_hp": 9500, "base_attack": 3500, "damage_type": "magical", "armor_defense": 80, "magic_defense": 10, "attack_range": 140, "attack_speed": 70, "attack_wait": 40, "attack_interval": 151, "move_speed": 350.0, "gain_cost": 3, "dot_rate": 1.5, "assassin_resist": 1, "transform_resist": 100, "pattern_id": 2119120, "race_id": 16, "special_effect_id": 222, "missile_id": 7, "missile": {"speed": 6.0, "splash": 133}, "master_id": 37686, "global_id": 11303, "ranged": true, "spawn_sec": 94}, {"enemy_id": 16, "source": "local", "count": 1, "form_count": 1, "hp": 8800, "attack": 2500, "base_hp": 8800, "base_attack": 2500, "damage_type": "physical", "armor_defense": 40, "magic_defense": 20, "attack_range": 260, "attack_speed": 1, "attack_wait": 90, "attack_interval": 253, "move_speed": 600.0, "gain_cost": 3, "dot_rate": 1.5, "assassin_resist": 1, "transform_resist": 100, "pattern_id": 2137680, "race_id": 16, "special_effect_id": 993, "missile_id": 560, "missile": {"speed": 6.0}, "master_id": 37665, "global_id": 11282, "ranged": true, "spawn_sec": 94}, {"enemy_id": 17, "source": "local", "count": 5, "form_count": 1, "tags": ["変異"], "hp": 28000, "attack": 800, "base_hp": 28000, "base_attack": 800, "damage_type": "physical", "armor_defense": 2000, "magic_defense": 10, "attack_speed": 60, "attack_wait": 60, "attack_interval": 236, "move_speed": 1500.0, "gain_cost": 2, "dot_rate": 1.5, "assassin_resist": 1000, "transform_resist": 1000, "pattern_id": 2129360, "race_id": 7, "special_effect_id": 68, "master_id": 34230, "global_id": 7847, "spawn_sec": 107}, {"enemy_id": 18, "source": "local", "count": 16, "form_count": 1, "tags": ["変異"], "hp": 3000, "attack": 200, "base_hp": 3000, "base_attack": 200, "damage_type": "physical", "armor_defense": 500, "magic_defense": 10, "attack_speed": 60, "attack_wait": 60, "attack_interval": 236, "move_speed": 1500.0, "gain_cost": 1, "dot_rate": 0.8999999761581421, "assassin_resist": 1000, "transform_resist": 1000, "pattern_id": 2129360, "race_id": 7, "special_effect_id": 66, "master_id": 33821, "global_id": 7438, "spawn_sec": 109}, {"enemy_id": 19, "source": "local", "count": 4, "form_count": 2, "tags": ["ステルス"], "hp": 12000, "attack": 800, "base_hp": 12000, "base_attack": 800, "damage_type": "physical", "armor_defense": 500, "magic_defense": 10, "attack_speed": 5, "attack_wait": 25, "attack_interval": 106, "move_speed": 400.0, "gain_cost": 2, "dot_rate": 1.5, "assassin_resist": 100, "transform_resist": 100, "pattern_id": 2103744, "race_id": 16, "special_effect_id": 61, "change_to": 19, "master_id": 32542, "global_id": 6161, "to_global_id": 6162, "route_behaviour": {"transforms": [{"wait": 1200}]}, "spawn_sec": 142}, {"enemy_id": 19, "source": "local", "count": 1, "form_index": 1, "form_count": 2, "hp": 12000, "attack": 800, "base_hp": 12000, "base_attack": 800, "damage_type": "physical", "armor_defense": 500, "magic_defense": 10, "attack_range": 180, "attack_speed": 90, "attack_wait": 60, "attack_interval": 211, "move_speed": 400.0, "gain_cost": 2, "dot_rate": 1.5, "assassin_resist": 100, "transform_resist": 100, "pattern_id": 2103712, "race_id": 16, "special_effect_id": 61, "change_to": 18, "missile_id": 46, "missile": {"speed": 12.0, "deflectable": true}, "master_id": 32543, "global_id": 6162, "ranged": true}, {"enemy_id": 21, "source": "local", "count": 4, "form_count": 2, "hp": 12000, "attack": 800, "base_hp": 12000, "base_attack": 800, "damage_type": "physical", "armor_defense": 500, "magic_defense": 10, "attack_speed": 5, "attack_wait": 25, "attack_interval": 106, "move_speed": 1000.0, "gain_cost": 2, "dot_rate": 1.5, "assassin_resist": 100, "transform_resist": 100, "pattern_id": 2109136, "race_id": 16, "special_effect_id": 61, "change_to": 21, "master_id": 32544, "global_id": 6163, "to_global_id": 6164, "route_behaviour": {"transforms": [{"wait": 1000}]}, "spawn_sec": 184}, {"enemy_id": 21, "source": "local", "count": 1, "form_index": 1, "form_count": 2, "hp": 12000, "attack": 1000, "base_hp": 12000, "base_attack": 1000, "damage_type": "physical", "armor_defense": 500, "magic_defense": 10, "attack_range": 300, "attack_speed": 90, "attack_wait": 135, "attack_interval": 361, "move_speed": 1000.0, "gain_cost": 2, "dot_rate": 1.5, "assassin_resist": 100, "transform_resist": 100, "pattern_id": 2109152, "race_id": 16, "special_effect_id": 61, "change_to": 20, "missile_id": 26, "master_id": 32545, "global_id": 6164, "ranged": true}], "popups": ["警戒中の見張りローグが、\n一度攻撃を行うと全ての敵の\n攻撃力と防御力がアップします。 "], "active": true}