{"quest_id": 9607, "name": "зҘһзҚЈгғҗгғҸгғ гғҲйҷҚиҮЁгҖҖзҘһзҙҡEX", "description": "пјңж·ұжө·(EX)пјҡж”»ж’ғеҫҢгҒ®еҫ…гҒЎжҷӮй–“гҒҢеў—еҠ \nгҖҖжҷӮй–“зөҢйҒҺгҒ§пјЁпј°гҒ«з¶ҷз¶ҡгғҖгғЎгғјгӮёпјһ\nпјңзү№е®ҡгҒ®гӮҝгӮӨгғҹгғігӮ°гҒ§жҝҖжөҒгҒҢзҷәз”ҹпјһ\nпјңжҷӮй–“зөҢйҒҺгҒ«гӮҲгӮӢгӮігӮ№гғҲеӣһеҫ©гҒӘгҒ—пјһ", "modifier_notes": ["ж·ұжө·(EX)пјҡж”»ж’ғеҫҢгҒ®еҫ…гҒЎжҷӮй–“гҒҢеў—еҠ \nгҖҖжҷӮй–“зөҢйҒҺгҒ§пјЁпј°гҒ«з¶ҷз¶ҡгғҖгғЎгғјгӮё", "зү№е®ҡгҒ®гӮҝгӮӨгғҹгғігӮ°гҒ§жҝҖжөҒгҒҢзҷәз”ҹ", "жҷӮй–“зөҢйҒҺгҒ«гӮҲгӮӢгӮігӮ№гғҲеӣһеҫ©гҒӘгҒ—"], "event": "зҘһзҚЈгғҗгғҸгғ гғҲйҷҚиҮЁ", "event_category": "Raid", "mission_id": 900312, "map_no": 9268, "level": 200, "multiplier": 2.0, "charisma": 25, "capacity": 10, "modifiers": [{"kind": "term", "influence": 34, "params": [0, 20, 6], "ext": "ж”»ж’ғеҫ…гҒЎеў—еҠ =120,гғҖгғЎгғјгӮёй–Ӣе§Ӣеҫ…гҒЎ=600"}, {"kind": "term", "influence": 35, "params": [100]}, {"kind": "term", "influence": 36, "params": [100]}, {"kind": "term", "influence": 17}], "enemies": [{"enemy_id": 1, "source": "local", "count": 1, "form_count": 1, "tags": ["гӮ№гғҶгғ«гӮ№", "зҪ®зү©"], "fixture": true, "hp": 200000, "attack": 2, "base_hp": 100000, "base_attack": 1, "damage_type": "physical", "attack_speed": 1, "attack_wait": 1, "move_speed": 200.0, "gain_cost": 1, "dot_rate": 1.0, "pattern_id": 2126800, "special_effect_id": 701, "master_id": 33290, "global_id": 6907, "route_behaviour": {"reroutes": ["Route=1", "Route=2"]}}, {"enemy_id": 2, "source": "local", "count": 1, "form_count": 6, "tags": ["гғ–гғӯгғғгӮҜдёҚеҸҜ", "зӢҷгҒҶ", "ж°ҙдёӯ"], "hp": 800000, "attack": 3000, "base_hp": 400000, "base_attack": 3000, "damage_type": "magical", "armor_defense": 900, "magic_defense": 40, "attack_range": 210, "attack_speed": 1, "attack_wait": 90, "attack_interval": 293, "move_speed": 60.0, "gain_cost": 3, "dot_rate": 1.5, "pattern_id": 2128656, "race_id": 15, "special_effect_id": 800, "change_to": 2, "missile_id": 547, "master_id": 36103, "global_id": 9720, "ranged": true, "to_global_id": 9721, "route_behaviour": {"transforms": [{"wait": 120}], "sets_flags": [[1, 1, 25000], [2, 1, 25000]], "calls_event": [2030, 2031, 2032, 2033]}}, {"enemy_id": 2, "source": "local", "count": 1, "form_index": 1, "form_count": 6, "tags": ["гғ–гғӯгғғгӮҜдёҚеҸҜ", "зӢҷгҒҶ", "ж°ҙдёӯ"], "hp": 800000, "attack": 6000, "base_hp": 400000, "base_attack": 3000, "damage_type": "magical", "armor_defense": 900, "magic_defense": 40, "attack_speed": 1, "attack_wait": 300, "attack_interval": 714, "move_speed": 60.0, "gain_cost": 3, "dot_rate": 1.5, "pattern_id": 2128768, "race_id": 15, "special_effect_id": 800, "change_to": 3, "missile_id": 547, "master_id": 36104, "global_id": 9721, "to_global_id": 9722}, {"enemy_id": 2, "source": "local", "count": 1, "form_index": 2, "form_count": 6, "tags": ["гғ–гғӯгғғгӮҜдёҚеҸҜ", "зӢҷгҒҶ", "ж°ҙдёӯ"], "hp": 800000, "attack": 26000, "base_hp": 400000, "base_attack": 26000, "damage_type": "magical", "armor_defense": 900, "magic_defense": 40, "attack_range": 210, "attack_speed": 1, "attack_wait": 12, "move_speed": 60.0, "gain_cost": 3, "dot_rate": 1.5, "pattern_id": 2128672, "race_id": 15, "special_effect_id": 801, "change_to": 4, "missile_id": 547, "master_id": 36105, "global_id": 9722, "ranged": true, "to_global_id": 9723}, {"enemy_id": 2, "source": "local", "count": 1, "form_index": 3, "form_count": 6, "tags": ["гғ–гғӯгғғгӮҜдёҚеҸҜ", "зӢҷгҒҶ", "ж°ҙдёӯ"], "hp": 800000, "attack": 26000, "base_hp": 400000, "base_attack": 26000, "damage_type": "magical", "armor_defense": 900, "magic_defense": 40, "attack_range": 400, "attack_speed": 1, "attack_wait": 12, "move_speed": 60.0, "gain_cost": 3, "dot_rate": 1.5, "pattern_id": 2128672, "race_id": 15, "special_effect_id": 801, "change_to": 5, "missile_id": 547, "master_id": 36106, "global_id": 9723, "ranged": true, "to_global_id": 9724}, {"enemy_id": 2, "source": "local", "count": 1, "form_index": 4, "form_count": 6, "tags": ["гғ–гғӯгғғгӮҜдёҚеҸҜ", "зӢҷгҒҶ", "ж°ҙдёӯ"], "hp": 800000, "attack": 26000, "base_hp": 400000, "base_attack": 26000, "damage_type": "magical", "armor_defense": 900, "magic_defense": 40, "attack_range": 600, "attack_speed": 1, "attack_wait": 12, "move_speed": 60.0, "gain_cost": 3, "dot_rate": 1.5, "pattern_id": 2128672, "race_id": 15, "special_effect_id": 801, "change_to": 6, "missile_id": 547, "master_id": 36107, "global_id": 9724, "ranged": true, "to_global_id": 9725}, {"enemy_id": 2, "source": "local", "count": 1, "form_index": 5, "form_count": 6, "tags": ["гғ–гғӯгғғгӮҜдёҚеҸҜ", "зӢҷгҒҶ", "ж°ҙдёӯ"], "hp": 800000, "attack": 26000, "base_hp": 400000, "base_attack": 26000, "damage_type": "magical", "armor_defense": 900, "magic_defense": 40, "attack_range": 900, "attack_speed": 1, "attack_wait": 12, "move_speed": 60.0, "gain_cost": 3, "dot_rate": 1.5, "pattern_id": 2128672, "race_id": 15, "special_effect_id": 801, "missile_id": 547, "master_id": 36108, "global_id": 9725, "ranged": true}, {"enemy_id": 8, "source": "local", "count": 8, "form_count": 1, "tags": ["зҪ®зү©"], "fixture": true, "hp": 120000, "base_hp": 60000, "damage_type": "physical", "armor_defense": 10, "magic_defense": 5, "attack_range": 80, "attack_speed": 25, "move_speed": 800.0, "gain_cost": 3, "dot_rate": 1.5, "assassin_resist": 100, "transform_resist": 100, "pattern_id": 2126592, "special_effect_id": 662, "missile_id": 45, "master_id": 36109, "global_id": 9726, "ranged": true, "spawn_sec": 4}, {"enemy_id": 9, "source": "local", "count": 1, "level": 50, "form_count": 1, "tags": ["гӮўгғјгғһгғј"], "hp": 540000, "attack": 1200, "base_hp": 270000, "base_attack": 1200, "damage_type": "magical", "armor_defense": 16000, "magic_defense": 50, "attack_range": 230, "attack_speed": 1, "attack_wait": 100, "attack_interval": 267, "move_speed": 50.0, "gain_cost": 3, "dot_rate": 1.399999976158142, "assassin_resist": 1, "transform_resist": 1, "pattern_id": 2126480, "race_id": 7, "change_to": 9, "change_condition": 1, "missile_id": 473, "missile": {"speed": 4.0, "splash": 133}, "master_id": 36110, "global_id": 9727, "ranged": true, "variants": [{"tags": ["гӮўгғјгғһгғј"], "hp": 540000, "attack": 9000, "base_hp": 270000, "base_attack": 4500, "damage_type": "physical", "armor_defense": 16000, "magic_defense": 50, "attack_speed": 1, "attack_wait": 125, "attack_interval": 313, "move_speed": 50.0, "gain_cost": 3, "dot_rate": 1.399999976158142, "assassin_resist": 1, "transform_resist": 1, "pattern_id": 2126464, "race_id": 7, "master_id": 36111, "global_id": 9728}], "spawn_sec": 8}, {"enemy_id": 11, "source": "local", "count": 9, "level": 80, "form_count": 1, "tags": ["гғ–гғӯгғғгӮҜдёҚеҸҜ", "зӢҷгҒҶ", "ж°ҙдёӯ"], "hp": 100000, "attack": 1000, "base_hp": 50000, "base_attack": 1000, "damage_type": "magical", "armor_defense": 2000, "magic_defense": 40, "attack_range": 200, "attack_speed": 1, "attack_wait": 50, "attack_interval": 151, "move_speed": 200.0, "gain_cost": 2, "dot_rate": 1.5, "assassin_resist": 100, "transform_resist": 100, "pattern_id": 2126544, "race_id": 7, "special_effect_id": 232, "missile_id": 481, "missile": {"speed": 1.0}, "master_id": 36112, "global_id": 9729, "ranged": true, "spawn_sec": 8}, {"enemy_id": 12, "source": "local", "count": 14, "form_count": 1, "hp": 36000, "attack": 1600, "base_hp": 18000, "base_attack": 1600, "damage_type": "physical", "armor_defense": 3500, "magic_defense": 20, "attack_range": 180, "attack_speed": 1, "attack_wait": 10, "attack_interval": 57, "move_speed": 2400.0, "gain_cost": 2, "dot_rate": 1.5, "assassin_resist": 1, "transform_resist": 100, "pattern_id": 2128976, "race_id": 7, "missile_id": 22, "missile": {"speed": 10.0}, "master_id": 36113, "global_id": 9730, "ranged": true, "spawn_sec": 12}, {"enemy_id": 13, "source": "local", "count": 20, "form_count": 2, "hp": 12000, "attack": 2200, "base_hp": 6000, "base_attack": 2200, "damage_type": "physical", "armor_defense": 200, "magic_defense": 35, "attack_range": 100, "attack_speed": 60, "attack_wait": 10, "attack_interval": 81, "move_speed": 800.0, "gain_cost": 2, "dot_rate": 1.2000000476837158, "assassin_resist": 100, "transform_resist": 100, "pattern_id": 2106544, "race_id": 7, "change_to": 13, "change_condition": 4, "missile_id": 139, "missile": {"speed": 5.0}, "master_id": 32616, "global_id": 6234, "ranged": true, "to_condition": 4, "to_ticks": 1, "to_global_id": 821, "spawn_sec": 16}, {"enemy_id": 13, "source": "local", "count": 1, "form_index": 1, "form_count": 2, "hp": 12000, "attack": 1200, "base_hp": 6000, "base_attack": 600, "damage_type": "physical", "armor_defense": 200, "magic_defense": 35, "attack_speed": 60, "attack_wait": 10, "attack_interval": 141, "move_speed": 800.0, "gain_cost": 1, "dot_rate": 1.2000000476837158, "assassin_resist": 100, "transform_resist": 100, "pattern_id": 2106528, "race_id": 7, "master_id": 822, "global_id": 821, "from_condition": 4, "trigger_ticks": 1}, {"enemy_id": 15, "source": "local", "count": 4, "form_count": 1, "tags": ["гғ–гғӯгғғгӮҜдёҚеҸҜ", "зӢҷгҒҶ", "ж°ҙдёӯ"], "hp": 30000, "attack": 1600, "base_hp": 15000, "base_attack": 1600, "damage_type": "magical", "armor_defense": 300, "magic_defense": 50, "attack_range": 250, "attack_speed": 1, "attack_wait": 50, "attack_interval": 166, "move_speed": 400.0, "gain_cost": 1, "dot_rate": 1.5, "assassin_resist": 1000, "transform_resist": 1000, "pattern_id": 2124416, "race_id": 7, "special_effect_id": 220, "missile_id": 480, "missile": {"speed": 3.0}, "master_id": 36114, "global_id": 9731, "ranged": true, "spawn_sec": 48}, {"enemy_id": 16, "source": "local", "count": 9, "form_count": 1, "tags": ["гғ–гғӯгғғгӮҜдёҚеҸҜ", "зӢҷгҒҶ", "ж°ҙдёӯ"], "hp": 6000, "attack": 800, "base_hp": 3000, "base_attack": 800, "damage_type": "physical", "armor_defense": 120, "magic_defense": 15, "attack_range": 60, "attack_speed": 1, "attack_wait": 20, "attack_interval": 71, "move_speed": 800.0, "gain_cost": 1, "dot_rate": 1.5, "assassin_resist": 1000, "transform_resist": 1000, "pattern_id": 2123728, "race_id": 7, "special_effect_id": 229, "missile_id": 232, "master_id": 36115, "global_id": 9732, "ranged": true, "spawn_sec": 51}, {"enemy_id": 17, "source": "local", "count": 13, "form_count": 3, "tags": ["ж°ҙжЈІ"], "hp": 14000, "attack": 1600, "base_hp": 7000, "base_attack": 800, "damage_type": "physical", "armor_defense": 300, "magic_defense": 10, "attack_speed": 1, "attack_wait": 90, "attack_interval": 376, "move_speed": 600.0, "gain_cost": 3, "dot_rate": 1.399999976158142, "assassin_resist": 100, "transform_resist": 100, "pattern_id": 2136464, "special_effect_id": 1019, "change_to": 17, "missile_id": 709, "missile": {"speed": 8.0}, "master_id": 36118, "global_id": 9735, "to_global_id": 9733, "route_behaviour": {"transforms": [{}]}, "spawn_sec": 143}, {"enemy_id": 17, "source": "local", "count": 1, "form_index": 1, "form_count": 3, "tags": ["ж°ҙжЈІ"], "hp": 14000, "attack": 800, "base_hp": 7000, "base_attack": 800, "damage_type": "physical", "armor_defense": 300, "magic_defense": 10, "attack_range": 900, "attack_speed": 1, "attack_wait": 90, "attack_interval": 375, "move_speed": 600.0, "gain_cost": 3, "dot_rate": 1.399999976158142, "assassin_resist": 100, "transform_resist": 100, "pattern_id": 2136464, "special_effect_id": 1019, "change_to": 18, "missile_id": 709, "missile": {"speed": 8.0}, "master_id": 36116, "global_id": 9733, "ranged": true, "to_global_id": 9734}, {"enemy_id": 17, "source": "local", "count": 1, "form_index": 2, "form_count": 3, "tags": ["ж°ҙжЈІ"], "hp": 14000, "attack": 800, "base_hp": 7000, "base_attack": 800, "damage_type": "physical", "armor_defense": 300, "magic_defense": 10, "attack_range": 900, "attack_speed": 1, "attack_wait": 90, "attack_interval": 375, "move_speed": 600.0, "gain_cost": 3, "dot_rate": 1.399999976158142, "assassin_resist": 100, "transform_resist": 100, "pattern_id": 2136704, "special_effect_id": 1028, "change_to": 17, "missile_id": 709, "missile": {"speed": 8.0}, "master_id": 36117, "global_id": 9734, "ranged": true}, {"enemy_id": 20, "source": "local", "count": 8, "form_count": 3, "tags": ["гғ–гғӯгғғгӮҜдёҚеҸҜ", "зӢҷгҒҶ", "ж°ҙдёӯ"], "hp": 40000, "attack": 1200, "base_hp": 20000, "base_attack": 1200, "damage_type": "physical", "armor_defense": 700, "magic_defense": 5, "attack_range": 80, "attack_speed": 1, "attack_wait": 180, "attack_interval": 404, "move_speed": 300.0, "dot_rate": 1.2999999523162842, "assassin_resist": 1500, "transform_resist": 1500, "pattern_id": 2124432, "race_id": 7, "change_to": 20, "change_condition": 4, "missile_id": 232, "master_id": 36119, "global_id": 9736, "ranged": true, "to_condition": 4, "to_ticks": 1, "to_global_id": 9737, "spawn_sec": 143}, {"enemy_id": 20, "source": "local", "count": 1, "form_index": 1, "form_count": 3, "tags": ["гғ–гғӯгғғгӮҜдёҚеҸҜ", "зӢҷгҒҶ", "ж°ҙдёӯ"], "hp": 40000, "attack": 1800, "base_hp": 20000, "base_attack": 1800, "damage_type": "physical", "armor_defense": 700, "magic_defense": 5, "attack_range": 80, "attack_speed": 1, "attack_wait": 180, "attack_interval": 404, "move_speed": 300.0, "dot_rate": 1.2999999523162842, "assassin_resist": 1500, "transform_resist": 1500, "pattern_id": 2124432, "race_id": 7, "special_effect_id": 554, "change_to": 21, "change_condition": 4, "missile_id": 232, "master_id": 36120, "global_id": 9737, "ranged": true, "from_condition": 4, "trigger_ticks": 1, "to_condition": 4, "to_ticks": 1, "to_global_id": 9738}, {"enemy_id": 20, "source": "local", "count": 1, "form_index": 2, "form_count": 3, "tags": ["гғ–гғӯгғғгӮҜдёҚеҸҜ", "зӢҷгҒҶ", "ж°ҙдёӯ"], "hp": 40000, "attack": 2700, "base_hp": 20000, "base_attack": 2700, "damage_type": "physical", "armor_defense": 700, "magic_defense": 5, "attack_range": 80, "attack_speed": 1, "attack_wait": 180, "attack_interval": 404, "move_speed": 300.0, "gain_cost": 1, "dot_rate": 1.2999999523162842, "assassin_resist": 1500, "transform_resist": 1500, "pattern_id": 2124432, "race_id": 7, "special_effect_id": 555, "missile_id": 232, "master_id": 36121, "global_id": 9738, "ranged": true, "from_condition": 4, "trigger_ticks": 1}, {"enemy_id": 23, "source": "local", "count": 27, "form_count": 2, "tags": ["ж°ҙжЈІ"], "hp": 12000, "attack": 800, "base_hp": 6000, "base_attack": 400, "damage_type": "physical", "armor_defense": 200, "magic_defense": 10, "attack_speed": 1, "attack_wait": 40, "attack_interval": 146, "move_speed": 400.0, "gain_cost": 1, "dot_rate": 1.5, "assassin_resist": 100, "transform_resist": 100, "pattern_id": 2136480, "change_to": 23, "change_condition": 5, "master_id": 36122, "global_id": 9739, "to_condition": 5, "to_global_id": 9740, "spawn_sec": 331}, {"enemy_id": 23, "source": "local", "count": 1, "form_index": 1, "form_count": 2, "tags": ["ж°ҙжЈІ"], "hp": 12000, "attack": 1800, "base_hp": 6000, "base_attack": 1800, "damage_type": "physical", "armor_defense": 800, "magic_defense": 30, "attack_range": 140, "attack_speed": 1, "attack_wait": 60, "attack_interval": 161, "move_speed": 500.0, "gain_cost": 1, "dot_rate": 1.5, "assassin_resist": 100, "transform_resist": 100, "pattern_id": 2136496, "special_effect_id": 232, "missile_id": 45, "master_id": 36123, "global_id": 9740, "ranged": true, "from_condition": 5}, {"enemy_id": 25, "source": "local", "count": 4, "form_count": 1, "tags": ["ж°ҙжЈІ", "гӮўгғјгғһгғј"], "hp": 50000, "attack": 3200, "base_hp": 25000, "base_attack": 1600, "damage_type": "physical", "armor_defense": 2500, "attack_speed": 1, "attack_wait": 15, "attack_interval": 78, "move_speed": 300.0, "gain_cost": 2, "dot_rate": 1.5, "assassin_resist": 100, "transform_resist": 100, "pattern_id": 2136512, "special_effect_id": 621, "master_id": 34854, "global_id": 8471, "route_behaviour": {"transforms": [{}]}, "spawn_sec": 433}], "active": true}